Workbook

Sheet Resumo
B1: Micron Technology (MU US) - Resumo do modelo
B2: US$ mn, exceto onde indicado | ano fiscal termina no inicio de setembro | FY26A nao auditado (8-K 30/set/26), 53 semanas
B4: Micron Technology | MU US | memoria DRAM/NAND/HBM
B5: Preco (US$) | D5: =Premissas!$I$203 -> 1045.56
B6: Data do preco | D6: =Premissas!$I$204 -> 06/10/26
B7: Preco-alvo 12m (US$) | D7: =DCF!I36 -> 997.23667
B8: Upside | D8: =DCF!I38 -> -0.046217651
B9: Mkt cap (US$ bn) | D9: =Multiplos!$D$7/1000 -> 1180.845
B10: EV (US$ bn) | D10: =Multiplos!$D$10/1000 -> 1112.571
B11: Net cash FY26A (US$ bn) | D11: =Multiplos!$D$11/1000 -> 68.274
B12: Cenario ativo | D12: =Premissas!$E$4 -> Base
B13: Analista | D13: LF
B14: Atualizado | D14: 07/out/26
B15: Checks | D15: =IF(AND(BP!$D$31="ok",FC!$D$41="ok",Operacional!$D$51="ok",DCF!D70="ok",DCF!D80="ok"),"Checks: ok","Checks: ERRO") -> Checks: ok
B17: US$ mn, exceto onde indicado | D17: FY24A | E17: FY25A | F17: FY26A | G17: FY27E | H17: FY28E | I17: FY29E
B18: Rec. liq. | D18: =DRE!F5 -> 25111 | E18: =DRE!G5 -> 37378 | F18: =DRE!H5 -> 133188 | G18: =DRE!I5 -> 272846.64 | H18: =DRE!J5 -> 300523.29 | I18: =DRE!K5 -> 213415.17
B19: cresc. a/a | D19: =DRE!F6 -> 0.61589447 | E19: =DRE!G6 -> 0.48851101 | F19: =DRE!H6 -> 2.5632725 | G19: =DRE!I6 -> 1.0485828 | H19: =DRE!J6 -> 0.10143663 | I19: =DRE!K6 -> -0.2898548
B20: MB | D20: =DRE!F9 -> 0.22352754 | E20: =DRE!G9 -> 0.39790786 | F20: =DRE!H9 -> 0.8071598 | G20: =DRE!I9 -> 0.86806508 | H20: =DRE!J9 -> 0.86168052 | I20: =DRE!K9 -> 0.76963004
B21: EBITDA | D21: =DRE!F16 -> 9084 | E21: =DRE!G16 -> 18122 | F21: =DRE!H16 -> 108843 | G21: =DRE!I16 -> 239428.96 | H21: =DRE!J16 -> 264842.99 | I21: =DRE!K16 -> 175963.25
B22: mg EBITDA | D22: =DRE!F17 -> 0.36175381 | E22: =DRE!G17 -> 0.48483065 | F22: =DRE!H17 -> 0.81721326 | G22: =DRE!I17 -> 0.87752211 | H22: =DRE!J17 -> 0.88127278 | I22: =DRE!K17 -> 0.82451144
B23: EBIT | D23: =DRE!F13 -> 1304 | E23: =DRE!G13 -> 9770 | F23: =DRE!H13 -> 99340 | G23: =DRE!I13 -> 226956.89 | H23: =DRE!J13 -> 247874.73 | I23: =DRE!K13 -> 152944.1
B24: LL | D24: =DRE!F26 -> 778 | E24: =DRE!G26 -> 8539 | F24: =DRE!H26 -> 84969 | G24: =DRE!I26 -> 194259.89 | H24: =DRE!J26 -> 213016.79 | I24: =DRE!K26 -> 134423.45
B25: EPS non-GAAP (US$) | D25: =DRE!F39 -> 1.3 | E25: =DRE!G39 -> 8.29 | F25: =DRE!H39 -> 75.52 | G25: =DRE!I39 -> 175.75508 | H25: =DRE!J39 -> 212.04296 | I25: =DRE!K39 -> 153.77844
B26: cresc. EPS non-GAAP | D26: =DRE!F40 -> n.m. | E26: =DRE!G40 -> 5.3769231 | F26: =DRE!H40 -> 8.1097708 | G26: =DRE!I40 -> 1.3272653 | H26: =DRE!J40 -> 0.20646844 | I26: =DRE!K40 -> -0.27477695
B27: FCF | D27: =FC!F23 -> 387 | E27: =FC!G23 -> 3725 | F27: =FC!H23 -> 62305 | G27: =FC!I23 -> 142703.04 | H27: =FC!J23 -> 173453.27 | I27: =FC!K23 -> 127996.86
B28: FCF yield | D28: =FC!F43 -> 0.00032773141 | E28: =FC!G43 -> 0.0031545207 | F28: =FC!H43 -> 0.052763063 | G28: =FC!I43 -> 0.12084824 | H28: =FC!J43 -> 0.14688911 | I28: =FC!K43 -> 0.10839429
B29: Net cash | D29: =BP!F33 -> -4245 | E29: =BP!G33 -> -2641 | F29: =BP!H33 -> 68274 | G29: =BP!I33 -> 125197.08 | H29: =BP!J33 -> 137735.54 | I29: =BP!K33 -> 144786.81
B30: EV/EBITDA (x) | D30: =IF(Multiplos!$D$10/DRE!F16>100,"n.m.",Multiplos!$D$10/DRE!F16) -> n.m. | E30: =IF(Multiplos!$D$10/DRE!G16>100,"n.m.",Multiplos!$D$10/DRE!G16) -> 61.39339 | F30: =IF(Multiplos!$D$10/DRE!H16>100,"n.m.",Multiplos!$D$10/DRE!H16) -> 10.221797 | G30: =IF(Multiplos!$D$10/DRE!I16>100,"n.m.",Multiplos!$D$10/DRE!I16) -> 4.6467687 | H30: =IF(Multiplos!$D$10/DRE!J16>100,"n.m.",Multiplos!$D$10/DRE!J16) -> 4.2008701 | I30: =IF(Multiplos!$D$10/DRE!K16>100,"n.m.",Multiplos!$D$10/DRE!K16) -> 6.3227465
B31: P/E non-GAAP (x) | D31: =IF(Premissas!$I$203/DRE!F39>100,"n.m.",Premissas!$I$203/DRE!F39) -> n.m. | E31: =IF(Premissas!$I$203/DRE!G39>100,"n.m.",Premissas!$I$203/DRE!G39) -> n.m. | F31: =IF(Premissas!$I$203/DRE!H39>100,"n.m.",Premissas!$I$203/DRE!H39) -> 13.844809 | G31: =IF(Premissas!$I$203/DRE!I39>100,"n.m.",Premissas!$I$203/DRE!I39) -> 5.9489604 | H31: =IF(Premissas!$I$203/DRE!J39>100,"n.m.",Premissas!$I$203/DRE!J39) -> 4.9308877 | I31: =IF(Premissas!$I$203/DRE!K39>100,"n.m.",Premissas!$I$203/DRE!K39) -> 6.7991327
B32: P/B (x) | D32: =Multiplos!$D$7/BP!F26 -> 26.164831 | E32: =Multiplos!$D$7/BP!G26 -> 21.800886 | F32: =Multiplos!$D$7/BP!H26 -> 8.5334736 | G32: =Multiplos!$D$7/BP!I26 -> 4.7452135 | H32: =Multiplos!$D$7/BP!J26 -> 3.8941495 | I32: =Multiplos!$D$7/BP!K26 -> 3.6992677
B33: Dividend yield | D33: =DRE!F42/Premissas!$I$203 -> 0.00043995562 | E33: =DRE!G42/Premissas!$I$203 -> 0.00043995562 | F33: =DRE!H42/Premissas!$I$203 -> 0.00050690539 | G33: =DRE!I42/Premissas!$I$203 -> 0.00066911512 | H33: =DRE!J42/Premissas!$I$203 -> 0.0008631585 | I33: =DRE!K42/Premissas!$I$203 -> 0.001018527
B35: Cenarios (snapshot 07/out/26 - atualizar ao mudar premissas)
B36: Cenario | D36: PT 12m (US$) | E36: Upside | F36: Rec. FY27E | G36: EPS ng FY27E | H36: MB FY27E | I36: EPS ng FY28E
B37: Base | D37: 997.23667 | E37: -0.046217651 | F37: 272846.64 | G37: 175.75508 | H37: 0.86806508 | I37: 212.04296
B38: Bull | D38: 1592.6122 | E38: 0.52321458 | F38: 284750.18 | G38: 185.0182 | H38: 0.87449708 | I38: 260.09139
B39: Bear | D39: 450.65501 | E39: -0.56898216 | F39: 244804.95 | G39: 154.26972 | H39: 0.85305869 | I39: 101.99196
B40: snapshot 07/out/26 - valores em azul lidos do modelo com Premissas!D4 = 1/2/3; cenario ativo acima e vivo
B42: Tese
B43: - FY27E ~75% contratado: guia 1T27 (61,5 bi; MB 86,25% non-GAAP como piso do ano) + carry-over de preco (saida 4T26 +46% DRAM / +60% NAND vs media FY26) entregam ~273 bi e MB ~87% sem alta adicional relevante - FY27 e o pico de margem e o risco de estimativa nele e pequeno.
B44: - Pico de receita e o FY28E (~300 bi), nao o FY27: ASP de DRAM sobe ate CQ4'27, mas a oferta nova (ID1/Tongluo, M15X/Yongin, P5, CXMT ~420k wpm) chega em CQ1-CQ2'28 e o preco rola; NAND vira antes (2S27).
B45: - O ciclo nao acabou: ASP DRAM -54% em 2 anos (2018-20) e -48% em 12m (2023) sustentam o ajuste de FY29-30E (receita 213 -> 167 bi), mas o piso de MB (~68%) fica acima de qualquer pico anterior por floors das SCAs (>35% da receita ate 2030), HBM com preco anual e capex em obra civil.
B46: - Mesmo no vale do Base a empresa gera ~90 bi de LL e ~95 bi de FCF; net cash de 68 bi, fim das restricoes CHIPS em 9-dez-26 e '100% do caixa excedente' em recompras cortam a base de acoes ~40-45% ate FY31E - EPS normalizado muito menos ciclico que a receita.
B47: - A 5,9x o EPS FY27E de consenso a acao ja precifica um ciclo; a assimetria esta em quando/quanto o preco cai (Bear: vira em CQ2'27, MB 44% no FY30E) vs CY27-28 mais apertados que 2026 (Bull: pico de MB no FY28E, 88,6%).
B49: Riscos
B50: - Reversao de preco antes do previsto: spot DDR5 parado desde set/26 com contrato ainda subindo, tetos de LTA ao nivel de CQ2'26, bits em queda em mobile/client; cada -10% de ASP DRAM no FY28 = ~-24 bi de receita e ~-3 p.p. de MB (quase tudo no EBIT).
B51: - Oferta: Samsung (>110 tri won), SK hynix (high-40s tri won; M15X/Yongin) e CXMT (350k -> 500k wpm, G5 DUV em DDR5/LPDDR) expandem junto com a Micron (capex 27 -> 52 -> 58 bi); D&A sobe de 9,5 para ~23 bi ate FY29E independente do preco.
B52: - Demanda/IA: DRAM+NAND = 68% do capex de CSPs em 2027 (TrendForce) - participacao insustentavel; digestao de capex de hyperscalers atinge memoria primeiro; share de HBM caiu de 21% para 18% (Counterpoint 1T->2T26) com Samsung de volta no HBM4.
B53: - Contratos e politica: take-or-pay com 12,9 bi de depositos nunca testado num vale (renegociacao/litigio); CAC China, tarifas Sec. 232 e controles BIS; CHIPS condiciona recompras e grants a marcos; FY26 nao auditado e com 53 semanas (base inflada ~2% para o FY27).

Sheet Premissas
B1: Premissas operacionais, financeiras e de valuation
B2: listas FY27E-FY31E por cenario (premissas_final.json, 07/out/26); seletor em D4; o modelo so le a linha 'Selecionado'
B4: Cenario ativo (1=Base, 2=Bull, 3=Bear) | C4: seletor | D4: 1 | E4: =CHOOSE($D$4,"Base","Bull","Bear") -> Base
B6: US$ mn, exceto onde indicado | D6: FY22A | E6: FY23A | F6: FY24A | G6: FY25A | H6: FY26A | I6: FY27E | J6: FY28E | K6: FY29E | L6: FY30E | M6: FY31E
B7: DRAM - bit growth (a/a) | C7: %
B8: Base | I8: 0.15 | J8: 0.14 | K8: 0.11 | L8: 0.09 | M8: 0.16
B9: Bull | I9: 0.17 | J9: 0.19 | K9: 0.18 | L9: 0.14 | M9: 0.15
B10: Bear | I10: 0.14 | J10: 0.12 | K10: 0.08 | L10: 0.1 | M10: 0.17
B11: Selecionado | I11: =CHOOSE($D$4,I8,I9,I10) -> 0.15 | J11: =CHOOSE($D$4,J8,J9,J10) -> 0.14 | K11: =CHOOSE($D$4,K8,K9,K10) -> 0.11 | L11: =CHOOSE($D$4,L8,L9,L10) -> 0.09 | M11: =CHOOSE($D$4,M8,M9,M10) -> 0.16
B13: DRAM - ASP (a/a) | C13: %
B14: Base | I14: 0.76 | J14: 0.015 | K14: -0.35 | L14: -0.3 | M14: 0.06
B15: Bull | I15: 0.8 | J15: 0.1 | K15: -0.12 | L15: -0.3 | M15: -0.14
B16: Bear | I16: 0.58 | J16: -0.36 | K16: -0.42 | L16: -0.16 | M16: 0.1
B17: Selecionado | I17: =CHOOSE($D$4,I14,I15,I16) -> 0.76 | J17: =CHOOSE($D$4,J14,J15,J16) -> 0.015 | K17: =CHOOSE($D$4,K14,K15,K16) -> -0.35 | L17: =CHOOSE($D$4,L14,L15,L16) -> -0.3 | M17: =CHOOSE($D$4,M14,M15,M16) -> 0.06
B19: DRAM - custo/bit (a/a) | C19: %
B20: Base | I20: 0.24 | J20: 0.02 | K20: 0.07 | L20: -0.02 | M20: -0.09
B21: Bull | I21: 0.21 | J21: -0.03 | K21: -0.03 | L21: 0.03 | M21: -0.06
B22: Bear | I22: 0.25 | J22: 0.07 | K22: 0.1 | L22: -0.01 | M22: -0.11
B23: Selecionado | I23: =CHOOSE($D$4,I20,I21,I22) -> 0.24 | J23: =CHOOSE($D$4,J20,J21,J22) -> 0.02 | K23: =CHOOSE($D$4,K20,K21,K22) -> 0.07 | L23: =CHOOSE($D$4,L20,L21,L22) -> -0.02 | M23: =CHOOSE($D$4,M20,M21,M22) -> -0.09
B25: NAND - bit growth (a/a) | C25: %
B26: Base | I26: 0.18 | J26: 0.17 | K26: 0.11 | L26: 0.12 | M26: 0.19
B27: Bull | I27: 0.19 | J27: 0.2 | K27: 0.16 | L27: 0.13 | M27: 0.15
B28: Bear | I28: 0.16 | J28: 0.1 | K28: 0.07 | L28: 0.1 | M28: 0.18
B29: Selecionado | I29: =CHOOSE($D$4,I26,I27,I28) -> 0.18 | J29: =CHOOSE($D$4,J26,J27,J28) -> 0.17 | K29: =CHOOSE($D$4,K26,K27,K28) -> 0.11 | L29: =CHOOSE($D$4,L26,L27,L28) -> 0.12 | M29: =CHOOSE($D$4,M26,M27,M28) -> 0.19
B31: NAND - ASP (a/a) | C31: %
B32: Base | I32: 0.82 | J32: -0.2 | K32: -0.4 | L32: -0.24 | M32: 0.08
B33: Bull | I33: 0.9 | J33: -0.05 | K33: -0.18 | L33: -0.3 | M33: -0.12
B34: Bear | I34: 0.7 | J34: -0.44 | K34: -0.44 | L34: -0.15 | M34: 0.12
B35: Selecionado | I35: =CHOOSE($D$4,I32,I33,I34) -> 0.82 | J35: =CHOOSE($D$4,J32,J33,J34) -> -0.2 | K35: =CHOOSE($D$4,K32,K33,K34) -> -0.4 | L35: =CHOOSE($D$4,L32,L33,L34) -> -0.24 | M35: =CHOOSE($D$4,M32,M33,M34) -> 0.08
B37: NAND - custo/bit (a/a) | C37: %
B38: Base | I38: 0.14 | J38: -0.03 | K38: 0.06 | L38: -0.02 | M38: -0.09
B39: Bull | I39: 0.12 | J39: -0.05 | K39: -0.04 | L39: 0.02 | M39: -0.07
B40: Bear | I40: 0.16 | J40: 0.03 | K40: 0.08 | L40: -0.02 | M40: -0.11
B41: Selecionado | I41: =CHOOSE($D$4,I38,I39,I40) -> 0.14 | J41: =CHOOSE($D$4,J38,J39,J40) -> -0.03 | K41: =CHOOSE($D$4,K38,K39,K40) -> 0.06 | L41: =CHOOSE($D$4,L38,L39,L40) -> -0.02 | M41: =CHOOSE($D$4,M38,M39,M40) -> -0.09
B43: Outras receitas - cresc. (a/a) | C43: %
B44: Base | I44: 0.12 | J44: 0.04 | K44: -0.12 | L44: -0.08 | M44: 0.07
B45: Bull | I45: 0.18 | J45: 0.08 | K45: 0 | L45: -0.08 | M45: 0.04
B46: Bear | I46: 0.08 | J46: -0.12 | K46: -0.2 | L46: -0.05 | M46: 0.08
B47: Selecionado | I47: =CHOOSE($D$4,I44,I45,I46) -> 0.12 | J47: =CHOOSE($D$4,J44,J45,J46) -> 0.04 | K47: =CHOOSE($D$4,K44,K45,K46) -> -0.12 | L47: =CHOOSE($D$4,L44,L45,L46) -> -0.08 | M47: =CHOOSE($D$4,M44,M45,M46) -> 0.07
B49: R&D - cresc. (a/a) | C49: %
B50: Base | I50: 0.32 | J50: 0.13 | K50: 0.03 | L50: -0.02 | M50: 0.06
B51: Bull | I51: 0.34 | J51: 0.16 | K51: 0.09 | L51: 0.02 | M51: 0.03
B52: Bear | I52: 0.3 | J52: 0.04 | K52: -0.05 | L52: -0.06 | M52: 0.03
B53: Selecionado | I53: =CHOOSE($D$4,I50,I51,I52) -> 0.32 | J53: =CHOOSE($D$4,J50,J51,J52) -> 0.13 | K53: =CHOOSE($D$4,K50,K51,K52) -> 0.03 | L53: =CHOOSE($D$4,L50,L51,L52) -> -0.02 | M53: =CHOOSE($D$4,M50,M51,M52) -> 0.06
B55: SG&A - cresc. (a/a) | C55: %
B56: Base | I56: 0.25 | J56: 0.09 | K56: -0.01 | L56: -0.05 | M56: 0.05
B57: Bull | I57: 0.27 | J57: 0.11 | K57: 0.06 | L57: 0 | M57: 0.02
B58: Bear | I58: 0.23 | J58: 0.01 | K58: -0.07 | L58: -0.08 | M58: 0.03
B59: Selecionado | I59: =CHOOSE($D$4,I56,I57,I58) -> 0.25 | J59: =CHOOSE($D$4,J56,J57,J58) -> 0.09 | K59: =CHOOSE($D$4,K56,K57,K58) -> -0.01 | L59: =CHOOSE($D$4,L56,L57,L58) -> -0.05 | M59: =CHOOSE($D$4,M56,M57,M58) -> 0.05
B61: SBC (% receita) | C61: %
B62: Base | I62: 0.0073 | J62: 0.0076 | K62: 0.0117 | L62: 0.0153 | M62: 0.0133
B63: Bull | I63: 0.007 | J63: 0.0066 | K63: 0.007 | L63: 0.0094 | M63: 0.0107
B64: Bear | I64: 0.0078 | J64: 0.0115 | K64: 0.0175 | L64: 0.0195 | M64: 0.017
B65: Selecionado | I65: =CHOOSE($D$4,I62,I63,I64) -> 0.0073 | J65: =CHOOSE($D$4,J62,J63,J64) -> 0.0076 | K65: =CHOOSE($D$4,K62,K63,K64) -> 0.0117 | L65: =CHOOSE($D$4,L62,L63,L64) -> 0.0153 | M65: =CHOOSE($D$4,M62,M63,M64) -> 0.0133
B67: Capex liquido (US$ mn) | C67: US$ mn
B68: Base | I68: 52000 | J68: 58000 | K68: 38000 | L68: 30000 | M68: 36000
B69: Bull | I69: 54000 | J69: 66000 | K69: 60000 | L69: 42000 | M69: 38000
B70: Bear | I70: 49000 | J70: 40000 | K70: 25000 | L70: 21000 | M70: 25000
B71: Selecionado | I71: =CHOOSE($D$4,I68,I69,I70) -> 52000 | J71: =CHOOSE($D$4,J68,J69,J70) -> 58000 | K71: =CHOOSE($D$4,K68,K69,K70) -> 38000 | L71: =CHOOSE($D$4,L68,L69,L70) -> 30000 | M71: =CHOOSE($D$4,M68,M69,M70) -> 36000
B73: D&A (% PP&E liq. inicial) | C73: %
B74: Base | I74: 0.197 | J74: 0.165 | K74: 0.16 | L74: 0.17 | M74: 0.18
B75: Bull | I75: 0.197 | J75: 0.165 | K75: 0.165 | L75: 0.175 | M75: 0.185
B76: Bear | I76: 0.197 | J76: 0.168 | K76: 0.175 | L76: 0.185 | M76: 0.19
B77: Selecionado | I77: =CHOOSE($D$4,I74,I75,I76) -> 0.197 | J77: =CHOOSE($D$4,J74,J75,J76) -> 0.165 | K77: =CHOOSE($D$4,K74,K75,K76) -> 0.16 | L77: =CHOOSE($D$4,L74,L75,L76) -> 0.17 | M77: =CHOOSE($D$4,M74,M75,M76) -> 0.18
B79: Aliquota de IR | C79: %
B80: Base | I80: 0.155 | J80: 0.158 | K80: 0.15 | L80: 0.165 | M80: 0.155
B81: Bull | I81: 0.155 | J81: 0.16 | K81: 0.16 | L81: 0.155 | M81: 0.152
B82: Bear | I82: 0.155 | J82: 0.152 | K82: 0.185 | L82: 0.23 | M82: 0.17
B83: Selecionado | I83: =CHOOSE($D$4,I80,I81,I82) -> 0.155 | J83: =CHOOSE($D$4,J80,J81,J82) -> 0.158 | K83: =CHOOSE($D$4,K80,K81,K82) -> 0.15 | L83: =CHOOSE($D$4,L80,L81,L82) -> 0.165 | M83: =CHOOSE($D$4,M80,M81,M82) -> 0.155
B85: DSO (dias) | C85: dias
B86: Base | I86: 71 | J86: 64 | K86: 56 | L86: 55 | M86: 60
B87: Bull | I87: 72 | J87: 68 | K87: 66 | L87: 58 | M87: 56
B88: Bear | I88: 68 | J88: 60 | K88: 57 | L88: 57 | M88: 61
B89: Selecionado | I89: =CHOOSE($D$4,I86,I87,I88) -> 71 | J89: =CHOOSE($D$4,J86,J87,J88) -> 64 | K89: =CHOOSE($D$4,K86,K87,K88) -> 56 | L89: =CHOOSE($D$4,L86,L87,L88) -> 55 | M89: =CHOOSE($D$4,M86,M87,M88) -> 60
B91: DIO (dias) | C91: dias
B92: Base | I92: 131 | J92: 128 | K92: 158 | L92: 165 | M92: 142
B93: Bull | I93: 129 | J93: 124 | K93: 130 | L93: 150 | M93: 150
B94: Bear | I94: 136 | J94: 160 | K94: 175 | L94: 160 | M94: 140
B95: Selecionado | I95: =CHOOSE($D$4,I92,I93,I94) -> 131 | J95: =CHOOSE($D$4,J92,J93,J94) -> 128 | K95: =CHOOSE($D$4,K92,K93,K94) -> 158 | L95: =CHOOSE($D$4,L92,L93,L94) -> 165 | M95: =CHOOSE($D$4,M92,M93,M94) -> 142
B97: DPO (dias) | C97: dias
B98: Base | I98: 284 | J98: 250 | K98: 158 | L98: 138 | M98: 150
B99: Bull | I99: 288 | J99: 262 | K99: 232 | L99: 165 | M99: 140
B100: Bear | I100: 262 | J100: 165 | K100: 112 | L100: 102 | M100: 112
B101: Selecionado | I101: =CHOOSE($D$4,I98,I99,I100) -> 284 | J101: =CHOOSE($D$4,J98,J99,J100) -> 250 | K101: =CHOOSE($D$4,K98,K99,K100) -> 158 | L101: =CHOOSE($D$4,L98,L99,L100) -> 138 | M101: =CHOOSE($D$4,M98,M99,M100) -> 150
B103: Recompras (US$ mn) | C103: US$ mn
B104: Base | I104: 85000 | J104: 160000 | K104: 120000 | L104: 85000 | M104: 100000
B105: Bull | I105: 95000 | J105: 190000 | K105: 220000 | L105: 190000 | M105: 180000
B106: Bear | I106: 70000 | J106: 80000 | K106: 25000 | L106: 10000 | M106: 15000
B107: Selecionado | I107: =CHOOSE($D$4,I104,I105,I106) -> 85000 | J107: =CHOOSE($D$4,J104,J105,J106) -> 160000 | K107: =CHOOSE($D$4,K104,K105,K106) -> 120000 | L107: =CHOOSE($D$4,L104,L105,L106) -> 85000 | M107: =CHOOSE($D$4,M104,M105,M106) -> 100000
B109: DPS - cresc. (a/a) | C109: %
B110: Base | I110: 0.32 | J110: 0.29 | K110: 0.18 | L110: 0.06 | M110: 0.05
B111: Bull | I111: 0.32 | J111: 0.36 | K111: 0.22 | L111: 0.09 | M111: 0.05
B112: Bear | I112: 0.32 | J112: 0.07 | K112: 0 | L112: 0 | M112: 0.03
B113: Selecionado | I113: =CHOOSE($D$4,I110,I111,I112) -> 0.32 | J113: =CHOOSE($D$4,J110,J111,J112) -> 0.29 | K113: =CHOOSE($D$4,K110,K111,K112) -> 0.18 | L113: =CHOOSE($D$4,L110,L111,L112) -> 0.06 | M113: =CHOOSE($D$4,M110,M111,M112) -> 0.05
B115: Yield do caixa e aplicacoes | C115: %
B116: Base | I116: 0.043 | J116: 0.041 | K116: 0.038 | L116: 0.036 | M116: 0.036
B117: Bull | I117: 0.043 | J117: 0.042 | K117: 0.04 | L117: 0.037 | M117: 0.036
B118: Bear | I118: 0.042 | J118: 0.037 | K118: 0.032 | L118: 0.029 | M118: 0.03
B119: Selecionado | I119: =CHOOSE($D$4,I116,I117,I118) -> 0.043 | J119: =CHOOSE($D$4,J116,J117,J118) -> 0.041 | K119: =CHOOSE($D$4,K116,K117,K118) -> 0.038 | L119: =CHOOSE($D$4,L116,L117,L118) -> 0.036 | M119: =CHOOSE($D$4,M116,M117,M118) -> 0.036
B121: Custo medio da divida (juros/saldo medio) | C121: %
...

Sheet Operacional
B1: Operacional - receita, bits, ASP e margem bruta por produto
B2: FY26A: split DRAM/NAND de fonte secundaria do deck 4T26 (thelec), 'outros' derivado; indices FY26A = 100
B4: US$ mn, exceto onde indicado | D4: FY22A | E4: FY23A | F4: FY24A | G4: FY25A | H4: FY26A | I4: FY27E | J4: FY28E | K4: FY29E | L4: FY30E | M4: FY31E
B5: Receita por produto
B6: Receita DRAM | C6: 8-K/10-K | D6: 22386 | E6: 10978 | F6: 17600 | G6: 28578 | H6: 100679 | I6: =H6*(1+Premissas!I11)*(1+Premissas!I17) -> 203774.3 | J6: =I6*(1+Premissas!J11)*(1+Premissas!J17) -> 235787.24 | K6: =J6*(1+Premissas!K11)*(1+Premissas!K17) -> 170120.49 | L6: =K6*(1+Premissas!L11)*(1+Premissas!L17) -> 129801.94 | M6: =L6*(1+Premissas!M11)*(1+Premissas!M17) -> 159604.46
B7: Receita NAND | D7: 7811 | E7: 4206 | F7: 7230 | G7: 8503 | H7: 31785 | I7: =H7*(1+Premissas!I29)*(1+Premissas!I35) -> 68261.466 | J7: =I7*(1+Premissas!J29)*(1+Premissas!J35) -> 63892.732 | K7: =J7*(1+Premissas!K29)*(1+Premissas!K35) -> 42552.56 | L7: =K7*(1+Premissas!L29)*(1+Premissas!L35) -> 36220.739 | M7: =L7*(1+Premissas!M29)*(1+Premissas!M35) -> 46550.893
B8: Receita Outros (NOR, 3D XPoint ate FY22) | C8: derivado | D8: 561 | E8: 356 | F8: 281 | G8: 297 | H8: 724 | I8: =H8*(1+Premissas!I47) -> 810.88 | J8: =I8*(1+Premissas!J47) -> 843.3152 | K8: =J8*(1+Premissas!K47) -> 742.11738 | L8: =K8*(1+Premissas!L47) -> 682.74799 | M8: =L8*(1+Premissas!M47) -> 730.54034
B9: Rec. liq. total | D9: =SUM(D6:D8) -> 30758 | E9: =SUM(E6:E8) -> 15540 | F9: =SUM(F6:F8) -> 25111 | G9: =SUM(G6:G8) -> 37378 | H9: =SUM(H6:H8) -> 133188 | I9: =SUM(I6:I8) -> 272846.64 | J9: =SUM(J6:J8) -> 300523.29 | K9: =SUM(K6:K8) -> 213415.17 | ... M9: =SUM(M6:M8) -> 206885.89
B10: Rec. liq. reportada (memo) | D10: 30758 | E10: 15540 | F10: 25111 | G10: 37378 | H10: 133188
B11: Check: soma segmentos - reportada/DRE | D11: =D9-D10 -> 0 | E11: =E9-E10 -> 0 | F11: =F9-F10 -> 0 | G11: =G9-G10 -> 0 | H11: =H9-H10 -> 0 | I11: =I9-DRE!I5 -> 0 | J11: =J9-DRE!J5 -> 0 | K11: =K9-DRE!K5 -> 0 | L11: =L9-DRE!L5 -> 0 | M11: =M9-DRE!M5 -> 0
B12: cresc. DRAM a/a | E12: =IFERROR(E6/D6-1,"") -> -0.50960422 | F12: =IFERROR(F6/E6-1,"") -> 0.60320641 | G12: =IFERROR(G6/F6-1,"") -> 0.62375 | H12: =IFERROR(H6/G6-1,"") -> 2.5229547 | I12: =IFERROR(I6/H6-1,"") -> 1.024 | J12: =IFERROR(J6/I6-1,"") -> 0.1571 | K12: =IFERROR(K6/J6-1,"") -> -0.2785 | L12: =IFERROR(L6/K6-1,"") -> -0.237 | M12: =IFERROR(M6/L6-1,"") -> 0.2296
B13: cresc. NAND a/a | E13: =IFERROR(E7/D7-1,"") -> -0.46152861 | F13: =IFERROR(F7/E7-1,"") -> 0.7189729 | G13: =IFERROR(G7/F7-1,"") -> 0.17607192 | H13: =IFERROR(H7/G7-1,"") -> 2.7380924 | I13: =IFERROR(I7/H7-1,"") -> 1.1476 | J13: =IFERROR(J7/I7-1,"") -> -0.064 | K13: =IFERROR(K7/J7-1,"") -> -0.334 | L13: =IFERROR(L7/K7-1,"") -> -0.1488 | M13: =IFERROR(M7/L7-1,"") -> 0.2852
B14: cresc. total a/a | E14: =IFERROR(E9/D9-1,"") -> -0.49476559 | F14: =IFERROR(F9/E9-1,"") -> 0.61589447 | G14: =IFERROR(G9/F9-1,"") -> 0.48851101 | H14: =IFERROR(H9/G9-1,"") -> 2.5632725 | I14: =IFERROR(I9/H9-1,"") -> 1.0485828 | J14: =IFERROR(J9/I9-1,"") -> 0.10143663 | K14: =IFERROR(K9/J9-1,"") -> -0.2898548 | L14: =IFERROR(L9/K9-1,"") -> -0.21886798 | M14: =IFERROR(M9/L9-1,"") -> 0.24102678
B15: Mix DRAM (% receita) | D15: =D6/D9 -> 0.72781065 | E15: =E6/E9 -> 0.70643501 | F15: =F6/F9 -> 0.70088806 | G15: =G6/G9 -> 0.76456739 | H15: =H6/H9 -> 0.75591645 | I15: =I6/I9 -> 0.74684553 | J15: =J6/J9 -> 0.78458891 | K15: =K6/K9 -> 0.79713402 | ... M15: =M6/M9 -> 0.7714613
B16: Mix NAND (% receita) | D16: =D7/D9 -> 0.25395019 | E16: =E7/E9 -> 0.27065637 | F16: =F7/F9 -> 0.28792163 | G16: =G7/G9 -> 0.22748676 | H16: =H7/H9 -> 0.23864763 | I16: =I7/I9 -> 0.25018254 | J16: =J7/J9 -> 0.21260493 | K16: =K7/K9 -> 0.19938864 | ... M16: =M7/M9 -> 0.22500758
B18: Indices (FY26A = 100)
B19: DRAM - indice de bits | C19: FY26A=100 | H19: 100 | I19: =H19*(1+Premissas!I11) -> 115 | J19: =I19*(1+Premissas!J11) -> 131.1 | K19: =J19*(1+Premissas!K11) -> 145.521 | L19: =K19*(1+Premissas!L11) -> 158.61789 | M19: =L19*(1+Premissas!M11) -> 183.99675
B20: DRAM - indice de ASP | H20: 100 | I20: =H20*(1+Premissas!I17) -> 176 | J20: =I20*(1+Premissas!J17) -> 178.64 | K20: =J20*(1+Premissas!K17) -> 116.116 | L20: =K20*(1+Premissas!L17) -> 81.2812 | M20: =L20*(1+Premissas!M17) -> 86.158072
B21: DRAM - indice de custo/bit | H21: 100 | I21: =H21*(1+Premissas!I23) -> 124 | J21: =I21*(1+Premissas!J23) -> 126.48 | K21: =J21*(1+Premissas!K23) -> 135.3336 | L21: =K21*(1+Premissas!L23) -> 132.62693 | M21: =L21*(1+Premissas!M23) -> 120.6905
B22: NAND - indice de bits | H22: 100 | I22: =H22*(1+Premissas!I29) -> 118 | J22: =I22*(1+Premissas!J29) -> 138.06 | K22: =J22*(1+Premissas!K29) -> 153.2466 | L22: =K22*(1+Premissas!L29) -> 171.63619 | M22: =L22*(1+Premissas!M29) -> 204.24707
B23: NAND - indice de ASP | H23: 100 | I23: =H23*(1+Premissas!I35) -> 182 | J23: =I23*(1+Premissas!J35) -> 145.6 | K23: =J23*(1+Premissas!K35) -> 87.36 | L23: =K23*(1+Premissas!L35) -> 66.3936 | M23: =L23*(1+Premissas!M35) -> 71.705088
B24: NAND - indice de custo/bit | H24: 100 | I24: =H24*(1+Premissas!I41) -> 114 | J24: =I24*(1+Premissas!J41) -> 110.58 | K24: =J24*(1+Premissas!K41) -> 117.2148 | L24: =K24*(1+Premissas!L41) -> 114.8705 | M24: =L24*(1+Premissas!M41) -> 104.53216
B26: Margem bruta por produto: MB_t = 1 - (1-MB_t-1) x (1+custo/bit)/(1+ASP)
B27: MB DRAM | C27: estimativa | H27: =Premissas!$H$199 -> 0.815 | I27: =1-(1-H27)*(1+Premissas!I23)/(1+Premissas!I17) -> 0.86965909 | J27: =1-(1-I27)*(1+Premissas!J23)/(1+Premissas!J17) -> 0.86901702 | K27: =1-(1-J27)*(1+Premissas!K23)/(1+Premissas!K17) -> 0.78438186 | L27: =1-(1-K27)*(1+Premissas!L23)/(1+Premissas!L17) -> 0.6981346 | M27: =1-(1-L27)*(1+Premissas!M23)/(1+Premissas!M17) -> 0.7408514
B28: MB NAND | C28: backed out | H28: =(H34-H27*H6-H29*H8)/H7 -> 0.78590577 | I28: =1-(1-H28)*(1+Premissas!I41)/(1+Premissas!I35) -> 0.86589702 | J28: =1-(1-I28)*(1+Premissas!J41)/(1+Premissas!J35) -> 0.83740014 | K28: =1-(1-J28)*(1+Premissas!K41)/(1+Premissas!K35) -> 0.71274025 | L28: =1-(1-K28)*(1+Premissas!L41)/(1+Premissas!L35) -> 0.62958611 | M28: =1-(1-L28)*(1+Premissas!M41)/(1+Premissas!M35) -> 0.687892
B29: MB Outros | H29: =Premissas!$H$200 -> 0.65 | I29: =H29 -> 0.65 | J29: =I29 -> 0.65 | K29: =J29 -> 0.65 | L29: =K29 -> 0.65 | M29: =L29 -> 0.65
B30: LB DRAM | H30: =H6*H27 -> 82053.385 | I30: =I6*I27 -> 177214.17 | J30: =J6*J27 -> 204903.12 | K30: =K6*K27 -> 133439.43 | L30: =L6*L27 -> 90619.223 | M30: =M6*M27 -> 118243.19
B31: LB NAND | H31: =H7*H28 -> 24980.015 | I31: =I7*I28 -> 59107.4 | J31: =J7*J28 -> 53503.783 | K31: =K7*K28 -> 30328.922 | L31: =L7*L28 -> 22804.074 | M31: =M7*M28 -> 32021.987
B32: LB Outros | H32: =H8*H29 -> 470.6 | I32: =I8*I29 -> 527.072 | J32: =J8*J29 -> 548.15488 | K32: =K8*K29 -> 482.37629 | L32: =L8*L29 -> 443.78619 | M32: =M8*M29 -> 474.85122
B33: LB consolidado | D33: =D34 -> 13898 | E33: =E34 -> -1416 | F33: =F34 -> 5613 | G33: =G34 -> 14873 | H33: =SUM(H30:H32) -> 107504 | I33: =SUM(I30:I32) -> 236848.64 | J33: =SUM(J30:J32) -> 258955.06 | K33: =SUM(K30:K32) -> 164250.73 | L33: =SUM(L30:L32) -> 113867.08 | M33: =SUM(M30:M32) -> 150740.03
B34: LB reportado (memo) | D34: 13898 | E34: -1416 | F34: 5613 | G34: 14873 | H34: 107504
B35: MB consolidada | D35: =D33/D9 -> 0.45184993 | E35: =E33/E9 -> -0.091119691 | F35: =F33/F9 -> 0.22352754 | G35: =G33/G9 -> 0.39790786 | H35: =H33/H9 -> 0.8071598 | I35: =I33/I9 -> 0.86806508 | J35: =J33/J9 -> 0.86168052 | K35: =K33/K9 -> 0.76963004 | ... M35: =M33/M9 -> 0.72861433
B37: Receita por unidade de negocio (reorganizacao no 4T25: CMBU/CDBU/MCBU/AEBU; antes CNBU/MBU/EBU/SBU)
B38: CMBU - Cloud Memory | C38: est. | F38: n.d. | G38: n.d. | H38: 43101
B39: CDBU - Core Data Center | F39: n.d. | G39: n.d. | H39: 37595
B40: MCBU - Mobile & Client | F40: n.d. | G40: n.d. | H40: 36635
B41: AEBU - Automotive & Embedded | F41: n.d. | G41: n.d. | H41: 15858
B42: Total BUs | H42: =SUM(H38:H41) -> 133189
B43: mix CMBU | H43: =H38/H42 -> 0.32360781
B44: mix CDBU | H44: =H39/H42 -> 0.28226806
B45: mix MCBU | H45: =H40/H42 -> 0.27506025
B46: mix AEBU | H46: =H41/H42 -> 0.11906389
B48: HBM
B49: HBM - receita divulgada (texto, prepared remarks) | C49: remarks | F49: 3T24: >US$100 mn de HBM3E; sold out CY24/25 | G49: 2T25 >1,0 bi; 3T25 run-rate >6 bi anualizado; 4T25 ~2,0 bi | H49: sem US$ divulgado; 4T26 cresceu mais que a receita total; CY27 contratado com alta de preco
B51: Check segmentos (todas as colunas) | D51: =IF(SUMPRODUCT(ABS(D11:M11))<0.5,"ok","ERRO") -> ok

Sheet DRE
B1: DRE - demonstracao de resultados (GAAP) e ponte non-GAAP
B2: historico 8-K/10-K (FY26A nao auditado, 53 semanas); custos com sinal negativo
B4: US$ mn, exceto onde indicado | D4: FY22A | E4: FY23A | F4: FY24A | G4: FY25A | H4: FY26A | I4: FY27E | J4: FY28E | K4: FY29E | L4: FY30E | M4: FY31E
B5: Rec. liq. | D5: =Operacional!D9 -> 30758 | E5: =Operacional!E9 -> 15540 | F5: =Operacional!F9 -> 25111 | G5: =Operacional!G9 -> 37378 | H5: =Operacional!H9 -> 133188 | I5: =Operacional!I9 -> 272846.64 | J5: =Operacional!J9 -> 300523.29 | K5: =Operacional!K9 -> 213415.17 | ... M5: =Operacional!M9 -> 206885.89
B6: cresc. a/a | E6: =IFERROR(E5/D5-1,"") -> -0.49476559 | F6: =IFERROR(F5/E5-1,"") -> 0.61589447 | G6: =IFERROR(G5/F5-1,"") -> 0.48851101 | H6: =IFERROR(H5/G5-1,"") -> 2.5632725 | I6: =IFERROR(I5/H5-1,"") -> 1.0485828 | J6: =IFERROR(J5/I5-1,"") -> 0.10143663 | K6: =IFERROR(K5/J5-1,"") -> -0.2898548 | L6: =IFERROR(L5/K5-1,"") -> -0.21886798 | M6: =IFERROR(M5/L5-1,"") -> 0.24102678
B7: COGS | C7: 8-K/10-K | D7: -16860 | E7: -16956 | F7: -19498 | G7: -22505 | H7: -25684 | I7: =-(I5-Operacional!I33) -> -35998.001 | J7: =-(J5-Operacional!J33) -> -41568.225 | K7: =-(K5-Operacional!K33) -> -49164.443 | L7: =-(L5-Operacional!L33) -> -52838.339 | M7: =-(M5-Operacional!M33) -> -56145.867
B8: Lucro bruto (LB) | D8: =D5+D7 -> 13898 | E8: =E5+E7 -> -1416 | F8: =F5+F7 -> 5613 | G8: =G5+G7 -> 14873 | H8: =H5+H7 -> 107504 | I8: =I5+I7 -> 236848.64 | J8: =J5+J7 -> 258955.06 | K8: =K5+K7 -> 164250.73 | ... M8: =M5+M7 -> 150740.03
B9: MB | D9: =D8/D5 -> 0.45184993 | E9: =E8/E5 -> -0.091119691 | F9: =F8/F5 -> 0.22352754 | G9: =G8/G5 -> 0.39790786 | H9: =H8/H5 -> 0.8071598 | I9: =I8/I5 -> 0.86806508 | J9: =J8/J5 -> 0.86168052 | K9: =K8/K5 -> 0.76963004 | ... M9: =M8/M5 -> 0.72861433
B10: R&D | D10: -3116 | E10: -3114 | F10: -3430 | G10: -3798 | H10: -5650 | I10: =H10*(1+Premissas!I53) -> -7458 | J10: =I10*(1+Premissas!J53) -> -8427.54 | K10: =J10*(1+Premissas!K53) -> -8680.3662 | L10: =K10*(1+Premissas!L53) -> -8506.7589 | M10: =L10*(1+Premissas!M53) -> -9017.1644
B11: SG&A | D11: -1066 | E11: -920 | F11: -1129 | G11: -1205 | H11: -1947 | I11: =H11*(1+Premissas!I59) -> -2433.75 | J11: =I11*(1+Premissas!J59) -> -2652.7875 | K11: =J11*(1+Premissas!K59) -> -2626.2596 | L11: =K11*(1+Premissas!L59) -> -2494.9466 | M11: =L11*(1+Premissas!M59) -> -2619.694
B12: Outros op. / reestruturacao | D12: -14 | E12: -295 | F12: 250 | G12: -100 | H12: -567 | I12: =0 -> 0 | J12: =0 -> 0 | K12: =0 -> 0 | L12: =0 -> 0 | M12: =0 -> 0
B13: EBIT | D13: =D8+D10+D11+D12 -> 9702 | E13: =E8+E10+E11+E12 -> -5745 | F13: =F8+F10+F11+F12 -> 1304 | G13: =G8+G10+G11+G12 -> 9770 | H13: =H8+H10+H11+H12 -> 99340 | I13: =I8+I10+I11+I12 -> 226956.89 | J13: =J8+J10+J11+J12 -> 247874.73 | K13: =K8+K10+K11+K12 -> 152944.1 | ... M13: =M8+M10+M11+M12 -> 139103.17
B14: mg EBIT | D14: =D13/D5 -> 0.31543013 | E14: =E13/E5 -> -0.36969112 | F14: =F13/F5 -> 0.051929433 | G14: =G13/G5 -> 0.2613837 | H14: =H13/H5 -> 0.74586299 | I14: =I13/I5 -> 0.83181119 | J14: =J13/J5 -> 0.8248104 | K14: =K13/K5 -> 0.71665056 | ... M14: =M13/M5 -> 0.67236662
B15: D&A | C15: DFC | D15: 7116 | E15: 7756 | F15: 7780 | G15: 8352 | H15: 9503 | I15: =-Suporte!I10 -> 12472.07 | J15: =-Suporte!J10 -> 16968.258 | K15: =-Suporte!K10 -> 23019.147 | L15: =-Suporte!L10 -> 27004.589 | M15: =-Suporte!M10 -> 29132.268
B16: EBITDA | D16: =D13+D15 -> 16818 | E16: =E13+E15 -> 2011 | F16: =F13+F15 -> 9084 | G16: =G13+G15 -> 18122 | H16: =H13+H15 -> 108843 | I16: =I13+I15 -> 239428.96 | J16: =J13+J15 -> 264842.99 | K16: =K13+K15 -> 175963.25 | ... M16: =M13+M15 -> 168235.44
B17: mg EBITDA | D17: =D16/D5 -> 0.54678458 | E17: =E16/E5 -> 0.12940798 | F17: =F16/F5 -> 0.36175381 | G17: =G16/G5 -> 0.48483065 | H17: =H16/H5 -> 0.81721326 | I17: =I16/I5 -> 0.87752211 | J17: =J16/J5 -> 0.88127278 | K17: =K16/K5 -> 0.82451144 | ... M17: =M16/M5 -> 0.81317983
B18: Receita de juros (caixa e aplicacoes) | D18: 96 | E18: 468 | F18: 529 | G18: 496 | H18: 1084 | I18: =Suporte!I36 -> 3158.479 | J18: =Suporte!J36 -> 5325.2882 | K18: =Suporte!K36 -> 5412.0944 | L18: =Suporte!L36 -> 5381.093 | M18: =Suporte!M36 -> 5654.7085
B19: Despesa de juros | D19: -189 | E19: -388 | F19: -562 | G19: -477 | H19: -106 | I19: =Suporte!I33 -> -222.0075 | J19: =Suporte!J33 -> -210.96 | K19: =Suporte!K33 -> -210.96 | L19: =Suporte!L33 -> -210.96 | M19: =Suporte!M33 -> -205.0875
B20: Resultado financeiro | D20: =D18+D19 -> -93 | E20: =E18+E19 -> 80 | F20: =F18+F19 -> -33 | G20: =G18+G19 -> 19 | H20: =H18+H19 -> 978 | I20: =I18+I19 -> 2936.4715 | J20: =J18+J19 -> 5114.3282 | K20: =K18+K19 -> 5201.1344 | ... M20: =M18+M19 -> 5449.621
B21: Outros nao-operacionais | D21: -38 | E21: 7 | F21: -31 | G21: -135 | H21: -647 | I21: =0 -> 0 | J21: =0 -> 0 | K21: =0 -> 0 | L21: =0 -> 0 | M21: =0 -> 0
B22: LAIR | D22: =D13+D20+D21 -> 9571 | E22: =E13+E20+E21 -> -5658 | F22: =F13+F20+F21 -> 1240 | G22: =G13+G20+G21 -> 9654 | H22: =H13+H20+H21 -> 99671 | I22: =I13+I20+I21 -> 229893.36 | J22: =J13+J20+J21 -> 252989.06 | K22: =K13+K20+K21 -> 158145.23 | ... M22: =M13+M20+M21 -> 144552.79
B23: IR | D23: -888 | E23: -177 | F23: -451 | G23: -1124 | H23: -14761 | I23: =-I22*Premissas!I83 -> -35633.471 | J23: =-J22*Premissas!J83 -> -39972.272 | K23: =-K22*Premissas!K83 -> -23721.785 | L23: =-L22*Premissas!L83 -> -17825.859 | M23: =-M22*Premissas!M83 -> -22405.682
B24: aliquota efetiva | D24: =IFERROR(-D23/D22,"") -> 0.092780274 | E24: =IFERROR(-E23/E22,"") -> -0.031283139 | F24: =IFERROR(-F23/F22,"") -> 0.36370968 | G24: =IFERROR(-G23/G22,"") -> 0.11642842 | H24: =IFERROR(-H23/H22,"") -> 0.14809724 | I24: =IFERROR(-I23/I22,"") -> 0.155 | J24: =IFERROR(-J23/J22,"") -> 0.158 | K24: =IFERROR(-K23/K22,"") -> 0.15 | ... M24: =IFERROR(-M23/M22,"") -> 0.155
B25: Equivalencia patrimonial | D25: 4 | E25: 2 | F25: -11 | G25: 9 | H25: 59 | I25: =0 -> 0 | J25: =0 -> 0 | K25: =0 -> 0 | L25: =0 -> 0 | M25: =0 -> 0
B26: Lucro liquido (LL) | D26: =D22+D23+D25 -> 8687 | E26: =E22+E23+E25 -> -5833 | F26: =F22+F23+F25 -> 778 | G26: =G22+G23+G25 -> 8539 | H26: =H22+H23+H25 -> 84969 | I26: =I22+I23+I25 -> 194259.89 | J26: =J22+J23+J25 -> 213016.79 | K26: =K22+K23+K25 -> 134423.45 | ... M26: =M22+M23+M25 -> 122147.11
B27: mg liquida | D27: =D26/D5 -> 0.28243059 | E27: =E26/E5 -> -0.37535393 | F27: =F26/F5 -> 0.030982438 | G27: =G26/G5 -> 0.22844989 | H27: =H26/H5 -> 0.63796288 | I27: =I26/I5 -> 0.71197465 | J27: =J26/J5 -> 0.70881958 | K27: =K26/K5 -> 0.6298683 | ... M27: =M26/M5 -> 0.5904081
B28: cresc. LL a/a | E28: =IF(OR(D26<=0,E26<=0),"n.m.",E26/D26-1) -> n.m. | F28: =IF(OR(E26<=0,F26<=0),"n.m.",F26/E26-1) -> n.m. | G28: =IF(OR(F26<=0,G26<=0),"n.m.",G26/F26-1) -> 9.9755784 | H28: =IF(OR(G26<=0,H26<=0),"n.m.",H26/G26-1) -> 8.9506968 | I28: =IF(OR(H26<=0,I26<=0),"n.m.",I26/H26-1) -> 1.2862443 | J28: =IF(OR(I26<=0,J26<=0),"n.m.",J26/I26-1) -> 0.096555689 | K28: =IF(OR(J26<=0,K26<=0),"n.m.",K26/J26-1) -> -0.36895373 | L28: =IF(OR(K26<=0,L26<=0),"n.m.",L26/K26-1) -> -0.32891433 | M28: =IF(OR(L26<=0,M26<=0),"n.m.",M26/L26-1) -> 0.35403591
B30: Acoes diluidas (mn, media) | D30: 1122 | E30: 1093 | F30: 1118 | G30: 1125 | H30: 1143 | I30: =Suporte!I45 -> 1114.8636 | J30: =Suporte!J45 -> 1013.6621 | K30: =Suporte!K45 -> 887.93894 | L30: =Suporte!L45 -> 778.65605 | M30: =Suporte!M45 -> 676.97549
B31: EPS GAAP diluido (US$) | C31: reportado | D31: 7.75 | E31: -5.34 | F31: 0.7 | G31: 7.59 | H31: 74.33 | I31: =I26/I30 -> 174.24543 | J31: =J26/J30 -> 210.14577 | K31: =K26/K30 -> 151.38817 | L31: =L26/L30 -> 115.85302 | M31: =M26/M30 -> 180.43062
B32: cresc. EPS a/a | E32: =IF(OR(D31<=0,E31<=0),"n.m.",E31/D31-1) -> n.m. | F32: =IF(OR(E31<=0,F31<=0),"n.m.",F31/E31-1) -> n.m. | G32: =IF(OR(F31<=0,G31<=0),"n.m.",G31/F31-1) -> 9.8428571 | H32: =IF(OR(G31<=0,H31<=0),"n.m.",H31/G31-1) -> 8.7931489 | I32: =IF(OR(H31<=0,I31<=0),"n.m.",I31/H31-1) -> 1.344214 | J32: =IF(OR(I31<=0,J31<=0),"n.m.",J31/I31-1) -> 0.20603317 | K32: =IF(OR(J31<=0,K31<=0),"n.m.",K31/J31-1) -> -0.27960401 | L32: =IF(OR(K31<=0,L31<=0),"n.m.",L31/K31-1) -> -0.23472873 | M32: =IF(OR(L31<=0,M31<=0),"n.m.",M31/L31-1) -> 0.55740977
B34: Ponte non-GAAP
B35: (+) SBC | C35: DFC | D35: 514 | E35: 596 | F35: 833 | G35: 972 | H35: 1333 | I35: =I5*Premissas!I65 -> 1991.7805 | J35: =J5*Premissas!J65 -> 2283.977 | K35: =K5*Premissas!K65 -> 2496.9575 | L35: =L5*Premissas!L65 -> 2550.593 | M35: =M5*Premissas!M65 -> 2751.5824
B36: (+) Reestruturacao / outros ajustes | C36: hist: resid. | D36: =D38-D26-D35 -> 274 | E36: =E38-E26-E35 -> 375 | F36: =F38-F26-F35 -> -141 | G36: =G38-G26-G35 -> -41 | H36: =H38-H26-H35 -> 456 | I36: =0 -> 0 | J36: =0 -> 0 | K36: =0 -> 0 | L36: =0 -> 0 | M36: =0 -> 0
B37: (-) Efeito fiscal dos ajustes | I37: =-(I35+I36)*Premissas!I83 -> -308.72598 | J37: =-(J35+J36)*Premissas!J83 -> -360.86836 | K37: =-(K35+K36)*Premissas!K83 -> -374.54362 | L37: =-(L35+L36)*Premissas!L83 -> -420.84784 | M37: =-(M35+M36)*Premissas!M83 -> -426.49527
B38: LL non-GAAP | C38: reportado | D38: 9475 | E38: -4862 | F38: 1470 | G38: 9470 | H38: 86758 | I38: =I26+I35+I36+I37 -> 195942.95 | J38: =J26+J35+J36+J37 -> 214939.9 | K38: =K26+K35+K36+K37 -> 136545.86 | L38: =L26+L35+L36+L37 -> 92339.396 | M38: =M26+M35+M36+M37 -> 124472.19
B39: EPS non-GAAP (US$) | D39: 8.35 | E39: -4.45 | F39: 1.3 | G39: 8.29 | H39: 75.52 | I39: =I38/I30 -> 175.75508 | J39: =J38/J30 -> 212.04296 | K39: =K38/K30 -> 153.77844 | L39: =L38/L30 -> 118.58817 | M39: =M38/M30 -> 183.86514
B40: cresc. EPS non-GAAP a/a | E40: =IF(OR(D39<=0,E39<=0),"n.m.",E39/D39-1) -> n.m. | F40: =IF(OR(E39<=0,F39<=0),"n.m.",F39/E39-1) -> n.m. | G40: =IF(OR(F39<=0,G39<=0),"n.m.",G39/F39-1) -> 5.3769231 | H40: =IF(OR(G39<=0,H39<=0),"n.m.",H39/G39-1) -> 8.1097708 | I40: =IF(OR(H39<=0,I39<=0),"n.m.",I39/H39-1) -> 1.3272653 | J40: =IF(OR(I39<=0,J39<=0),"n.m.",J39/I39-1) -> 0.20646844 | K40: =IF(OR(J39<=0,K39<=0),"n.m.",K39/J39-1) -> -0.27477695 | L40: =IF(OR(K39<=0,L39<=0),"n.m.",L39/K39-1) -> -0.22883746 | M40: =IF(OR(L39<=0,M39<=0),"n.m.",M39/L39-1) -> 0.55045094
B42: DPS (US$) | D42: 0.415 | E42: 0.46 | F42: 0.46 | G42: 0.46 | H42: 0.53 | I42: =H42*(1+Premissas!I113) -> 0.6996 | J42: =I42*(1+Premissas!J113) -> 0.902484 | K42: =J42*(1+Premissas!K113) -> 1.0649311 | L42: =K42*(1+Premissas!L113) -> 1.128827 | M42: =L42*(1+Premissas!M113) -> 1.1852683
B43: Payout (DPS / EPS GAAP) | D43: =IF(D31<=0,"n.m.",D42/D31) -> 0.053548387 | E43: =IF(E31<=0,"n.m.",E42/E31) -> n.m. | F43: =IF(F31<=0,"n.m.",F42/F31) -> 0.65714286 | G43: =IF(G31<=0,"n.m.",G42/G31) -> 0.060606061 | H43: =IF(H31<=0,"n.m.",H42/H31) -> 0.0071303646 | I43: =IF(I31<=0,"n.m.",I42/I31) -> 0.0040150264 | J43: =IF(J31<=0,"n.m.",J42/J31) -> 0.0042945619 | K43: =IF(K31<=0,"n.m.",K42/K31) -> 0.0070344409 | ... M43: =IF(M31<=0,"n.m.",M42/M31) -> 0.0065691086

Sheet BP
B1: BP - balanco patrimonial
B2: historico 8-K/10-K (FY26A condensado do press release); caixa projetado = caixa anterior + variacao de caixa do FC
B4: US$ mn, exceto onde indicado | D4: FY22A | E4: FY23A | F4: FY24A | G4: FY25A | H4: FY26A | I4: FY27E | J4: FY28E | K4: FY29E | L4: FY30E | M4: FY31E
B5: Caixa e aplicacoes (CP + LP) | C5: proj: FC | D5: =SUM(D6:D8) -> 10978 | E5: =SUM(E6:E8) -> 10438 | F5: =SUM(F6:F8) -> 9152 | G5: =SUM(G6:G8) -> 11936 | H5: =SUM(H6:H8) -> 73453 | I5: =FC!I38 -> 129885.08 | J5: =FC!J38 -> 142423.54 | K5: =FC!K38 -> 149474.81 | L5: =FC!L38 -> 157075.24 | M5: =FC!M38 -> 170293.33
B6: memo: caixa e equivalentes | C6: 8-K/10-K | D6: 8262 | E6: 8577 | F6: 7041 | G6: 9642 | H6: 38364
B7: memo: aplicacoes de curto prazo | D7: 1069 | E7: 1017 | F7: 1065 | G7: 665 | H7: 5070
B8: memo: aplicacoes de longo prazo (marketable) | D8: 1647 | E8: 844 | F8: 1046 | G8: 1629 | H8: 30019
B9: Contas a receber | D9: 5130 | E9: 2443 | F9: 6615 | G9: 9265 | H9: 36197 | I9: =Suporte!I20 -> 53074.278 | J9: =Suporte!J20 -> 52694.494 | K9: =Suporte!K20 -> 32743.149 | L9: =Suporte!L20 -> 25119.995 | M9: =Suporte!M20 -> 34008.64
B10: Estoques | D10: 6663 | E10: 8387 | F10: 8875 | G10: 8355 | H10: 10372 | I10: =Suporte!I21 -> 12919.83 | J10: =Suporte!J21 -> 14577.35 | K10: =Suporte!K21 -> 21282.142 | L10: =Suporte!L21 -> 23885.825 | M10: =Suporte!M21 -> 21843.05
B11: Outros ativos circulantes | D11: 657 | E11: 820 | F11: 776 | G11: 914 | H11: 1067 | I11: =H11 -> 1067 | J11: =I11 -> 1067 | K11: =J11 -> 1067 | L11: =K11 -> 1067 | M11: =L11 -> 1067
B12: Ativo circulante (ex-aplicacoes LP) | D12: =D5-D8+D9+D10+D11 -> 21781 | E12: =E5-E8+E9+E10+E11 -> 21244 | F12: =F5-F8+F9+F10+F11 -> 24372 | G12: =G5-G8+G9+G10+G11 -> 28841 | H12: =H5-H8+H9+H10+H11 -> 91070 | I12: =I5-I8+I9+I10+I11 -> 196946.19 | J12: =J5-J8+J9+J10+J11 -> 210762.38 | K12: =K5-K8+K9+K10+K11 -> 204567.1 | ... M12: =M5-M8+M9+M10+M11 -> 227212.02
B13: Imobilizado liquido | D13: 38549 | E13: 37928 | F13: 39749 | G13: 46590 | H13: 63310 | I13: =Suporte!I11 -> 102837.93 | J13: =Suporte!J11 -> 143869.67 | K13: =Suporte!K11 -> 158850.52 | L13: =Suporte!L11 -> 161845.94 | M13: =Suporte!M11 -> 168713.67
B14: Goodwill e intangiveis | D14: 1649 | E14: 1554 | F14: 1566 | G14: 1603 | H14: 1150 | I14: =H14 -> 1150 | J14: =I14 -> 1150 | K14: =J14 -> 1150 | L14: =K14 -> 1150 | M14: =L14 -> 1150
B15: Outros ativos nao-circulantes | D15: 2657 | E15: 2684 | F15: 2683 | G15: 4135 | H15: 10339 | I15: =H15 -> 10339 | J15: =I15 -> 10339 | K15: =J15 -> 10339 | L15: =K15 -> 10339 | M15: =L15 -> 10339
B16: Ativo total | D16: =D5+D9+D10+D11+D13+D14+D15 -> 66283 | E16: =E5+E9+E10+E11+E13+E14+E15 -> 64254 | F16: =F5+F9+F10+F11+F13+F14+F15 -> 69416 | G16: =G5+G9+G10+G11+G13+G14+G15 -> 82798 | H16: =H5+H9+H10+H11+H13+H14+H15 -> 195888 | I16: =I5+I9+I10+I11+I13+I14+I15 -> 311273.12 | J16: =J5+J9+J10+J11+J13+J14+J15 -> 366121.05 | K16: =K5+K9+K10+K11+K13+K14+K15 -> 374906.62 | ... M16: =M5+M9+M10+M11+M13+M14+M15 -> 407414.69
B18: Fornecedores e provisoes | D18: 6090 | E18: 3958 | F18: 7299 | G18: 9649 | H18: 22605 | I18: =Suporte!I22 -> 28009.403 | J18: =Suporte!J22 -> 28471.387 | K18: =Suporte!K22 -> 21282.142 | L18: =Suporte!L22 -> 19977.235 | M18: =Suporte!M22 -> 23073.644
B19: Divida de curto prazo | D19: 103 | E19: 278 | F19: 431 | G19: 560 | H19: 491 | I19: =Suporte!I30 -> 0 | J19: =Suporte!J30 -> 0 | K19: =Suporte!K30 -> 0 | L19: =Suporte!L30 -> 261 | M19: =Suporte!M30 -> 1066
B20: Outros passivos circulantes | D20: 1346 | E20: 529 | F20: 1518 | G20: 1245 | H20: 4386 | I20: =H20 -> 4386 | J20: =I20 -> 4386 | K20: =J20 -> 4386 | L20: =K20 -> 4386 | M20: =L20 -> 4386
B21: Passivo circulante | D21: =D18+D19+D20 -> 7539 | E21: =E18+E19+E20 -> 4765 | F21: =F18+F19+F20 -> 9248 | G21: =G18+G19+G20 -> 11454 | H21: =H18+H19+H20 -> 27482 | I21: =I18+I19+I20 -> 32395.403 | J21: =J18+J19+J20 -> 32857.387 | K21: =K18+K19+K20 -> 25668.142 | ... M21: =M18+M19+M20 -> 28525.644
B22: Divida de longo prazo | D22: 6803 | E22: 13052 | F22: 12966 | G22: 14017 | H22: 4688 | I22: =Suporte!I31 -> 4688 | J22: =Suporte!J31 -> 4688 | K22: =Suporte!K31 -> 4688 | L22: =Suporte!L31 -> 4427 | M22: =Suporte!M31 -> 3361
B23: Passivos contratuais de clientes (depositos SCA) | C23: SCAs | D23: 0 | E23: 0 | F23: 0 | G23: 0 | H23: 12895 | I23: =H23 -> 12895 | J23: =I23 -> 12895 | K23: =J23 -> 12895 | L23: =K23 -> 12895 | M23: =L23 -> 12895
B24: Outros passivos nao-circulantes | D24: 2034 | E24: 2317 | F24: 2071 | G24: 3162 | H24: 12445 | I24: =H24 -> 12445 | J24: =I24 -> 12445 | K24: =J24 -> 12445 | L24: =K24 -> 12445 | M24: =L24 -> 12445
B25: Passivo total | D25: =D21+D22+D23+D24 -> 16376 | E25: =E21+E22+E23+E24 -> 20134 | F25: =F21+F22+F23+F24 -> 24285 | G25: =G21+G22+G23+G24 -> 28633 | H25: =H21+H22+H23+H24 -> 57510 | I25: =I21+I22+I23+I24 -> 62423.403 | J25: =J21+J22+J23+J24 -> 62885.387 | K25: =K21+K22+K23+K24 -> 55696.142 | ... M25: =M21+M22+M23+M24 -> 57226.644
B26: Patrimonio liquido | D26: 49907 | E26: 44120 | F26: 45131 | G26: 54165 | H26: 138378 | I26: =H26+DRE!I26+FC!I27+FC!I28+DRE!I35 -> 248849.71 | J26: =I26+DRE!J26+FC!J27+FC!J28+DRE!J35 -> 303235.67 | K26: =J26+DRE!K26+FC!K27+FC!K28+DRE!K35 -> 319210.48 | L26: =K26+DRE!L26+FC!L27+FC!L28+DRE!L35 -> 326091.76 | M26: =L26+DRE!M26+FC!M27+FC!M28+DRE!M35 -> 350188.05
B27: Passivo + PL | D27: =D25+D26 -> 66283 | E27: =E25+E26 -> 64254 | F27: =F25+F26 -> 69416 | G27: =G25+G26 -> 82798 | H27: =H25+H26 -> 195888 | I27: =I25+I26 -> 311273.12 | J27: =J25+J26 -> 366121.05 | K27: =K25+K26 -> 374906.62 | ... M27: =M25+M26 -> 407414.69
B29: Check: ativo - passivo - PL | D29: =D16-D25-D26 -> 0 | E29: =E16-E25-E26 -> 0 | F29: =F16-F25-F26 -> 0 | G29: =G16-G25-G26 -> 0 | H29: =H16-H25-H26 -> 0 | I29: =I16-I25-I26 -> 0 | J29: =J16-J25-J26 -> 0 | K29: =K16-K25-K26 -> 0 | ... M29: =M16-M25-M26 -> 0
B30: Check BP | D30: =IF(ABS(D29)<0.5,"ok","ERRO") -> ok | E30: =IF(ABS(E29)<0.5,"ok","ERRO") -> ok | F30: =IF(ABS(F29)<0.5,"ok","ERRO") -> ok | G30: =IF(ABS(G29)<0.5,"ok","ERRO") -> ok | H30: =IF(ABS(H29)<0.5,"ok","ERRO") -> ok | I30: =IF(ABS(I29)<0.5,"ok","ERRO") -> ok | J30: =IF(ABS(J29)<0.5,"ok","ERRO") -> ok | K30: =IF(ABS(K29)<0.5,"ok","ERRO") -> ok | ... M30: =IF(ABS(M29)<0.5,"ok","ERRO") -> ok
B31: Check BP (todos os anos) | D31: =IF(COUNTIF(D30:M30,"ok")=10,"ok","ERRO") -> ok
B33: memo: net cash (caixa e aplicacoes - divida) | D33: =D5-D19-D22 -> 4072 | E33: =E5-E19-E22 -> -2892 | F33: =F5-F19-F22 -> -4245 | G33: =G5-G19-G22 -> -2641 | H33: =H5-H19-H22 -> 68274 | I33: =I5-I19-I22 -> 125197.08 | J33: =J5-J19-J22 -> 137735.54 | K33: =K5-K19-K22 -> 144786.81 | ... M33: =M5-M19-M22 -> 165866.33

Sheet FC
B1: FC - fluxo de caixa (metodo indireto)
B2: historico 8-K/10-K; capex liquido na definicao da Micron (liquido de incentivos); FCF = FCO - capex liquido
B4: US$ mn, exceto onde indicado | D4: FY22A | E4: FY23A | F4: FY24A | G4: FY25A | H4: FY26A | I4: FY27E | J4: FY28E | K4: FY29E | L4: FY30E | M4: FY31E
B5: Lucro liquido | D5: =DRE!D26 -> 8687 | E5: =DRE!E26 -> -5833 | F5: =DRE!F26 -> 778 | G5: =DRE!G26 -> 8539 | H5: =DRE!H26 -> 84969 | I5: =DRE!I26 -> 194259.89 | J5: =DRE!J26 -> 213016.79 | K5: =DRE!K26 -> 134423.45 | ... M5: =DRE!M26 -> 122147.11
B6: (+) D&A | D6: =DRE!D15 -> 7116 | E6: =DRE!E15 -> 7756 | F6: =DRE!F15 -> 7780 | G6: =DRE!G15 -> 8352 | H6: =DRE!H15 -> 9503 | I6: =DRE!I15 -> 12472.07 | J6: =DRE!J15 -> 16968.258 | K6: =DRE!K15 -> 23019.147 | ... M6: =DRE!M15 -> 29132.268
B7: (+) SBC | D7: =DRE!D35 -> 514 | E7: =DRE!E35 -> 596 | F7: =DRE!F35 -> 833 | G7: =DRE!G35 -> 972 | H7: =DRE!H35 -> 1333 | I7: =DRE!I35 -> 1991.7805 | J7: =DRE!J35 -> 2283.977 | K7: =DRE!K35 -> 2496.9575 | ... M7: =DRE!M35 -> 2751.5824
B8: (+) Outros nao-caixa (hist.) | C8: n.d.=0 | E8: 1932 | I8: =0 -> 0 | J8: =0 -> 0 | K8: =0 -> 0 | L8: =0 -> 0 | M8: =0 -> 0
B9: (-) Var. contas a receber | D9: 190 | E9: 2763 | F9: -3581 | G9: -1776 | H9: -25206 | I9: =-(BP!I9-BP!H9) -> -16877.278 | J9: =-(BP!J9-BP!I9) -> 379.78445 | K9: =-(BP!K9-BP!J9) -> 19951.345 | L9: =-(BP!L9-BP!K9) -> 7623.1541 | M9: =-(BP!M9-BP!L9) -> -8888.6449
B10: (-) Var. estoques | D10: -2179 | E10: -3555 | F10: -488 | G10: 520 | H10: -2017 | I10: =-(BP!I10-BP!H10) -> -2547.8304 | J10: =-(BP!J10-BP!I10) -> -1657.5198 | K10: =-(BP!K10-BP!J10) -> -6704.7922 | L10: =-(BP!L10-BP!K10) -> -2603.6822 | M10: =-(BP!M10-BP!L10) -> 2042.775
B11: (-) Var. outros ativos | I11: =-(BP!I11-BP!H11)-(BP!I15-BP!H15)-(BP!I14-BP!H14) -> 0 | J11: =-(BP!J11-BP!I11)-(BP!J15-BP!I15)-(BP!J14-BP!I14) -> 0 | K11: =-(BP!K11-BP!J11)-(BP!K15-BP!J15)-(BP!K14-BP!J14) -> 0 | L11: =-(BP!L11-BP!K11)-(BP!L15-BP!K15)-(BP!L14-BP!K14) -> 0 | M11: =-(BP!M11-BP!L11)-(BP!M15-BP!L15)-(BP!M14-BP!L14) -> 0
B12: (+) Var. fornecedores e provisoes | D12: 744 | E12: -1302 | F12: 1915 | G12: 862 | H12: 8707 | I12: =BP!I18-BP!H18 -> 5404.4034 | J12: =BP!J18-BP!I18 -> 461.98381 | K12: =BP!K18-BP!J18 -> -7189.2447 | L12: =BP!L18-BP!K18 -> -1304.9073 | M12: =BP!M18-BP!L18 -> 3096.4088
B13: (+) Var. outros passivos / demais (hist. inclui outros) | C13: DFC | D13: 109 | E13: -798 | F13: 1270 | G13: 56 | H13: 12386 | I13: =(BP!I20-BP!H20)+(BP!I24-BP!H24)+(BP!I23-BP!H23) -> 0 | J13: =(BP!J20-BP!I20)+(BP!J24-BP!I24)+(BP!J23-BP!I23) -> 0 | K13: =(BP!K20-BP!J20)+(BP!K24-BP!J24)+(BP!K23-BP!J23) -> 0 | L13: =(BP!L20-BP!K20)+(BP!L24-BP!K24)+(BP!L23-BP!K23) -> 0 | M13: =(BP!M20-BP!L20)+(BP!M24-BP!L24)+(BP!M23-BP!L23) -> 0
B14: FCO | D14: =SUM(D5:D13) -> 15181 | E14: =SUM(E5:E13) -> 1559 | F14: =SUM(F5:F13) -> 8507 | G14: =SUM(G5:G13) -> 17525 | H14: =SUM(H5:H13) -> 89675 | I14: =SUM(I5:I13) -> 194703.04 | J14: =SUM(J5:J13) -> 231453.27 | K14: =SUM(K5:K13) -> 165996.86 | ... M14: =SUM(M5:M13) -> 150281.5
B15: memo: FCO reportado | D15: 15181 | E15: 1559 | F15: 8507 | G15: 17525 | H15: 89675
B17: (-) Capex liquido | C17: liq. incent. | D17: -11980 | E17: -7010 | F17: -8120 | G17: -13800 | H17: -27370 | I17: =-Premissas!I71 -> -52000 | J17: =-Premissas!J71 -> -58000 | K17: =-Premissas!K71 -> -38000 | L17: =-Premissas!L71 -> -30000 | M17: =-Premissas!M71 -> -36000
B18: (-) Aplicacoes financeiras liquidas (hist.) | E18: 868 | F18: -205 | G18: -192 | H18: -32883 | I18: =0 -> 0 | J18: =0 -> 0 | K18: =0 -> 0 | L18: =0 -> 0 | M18: =0 -> 0
B19: Outros investimentos (hist.: residual) | D19: =D21-D17-D18 -> 395 | E19: =E21-E17-E18 -> -49 | F19: =F21-F17-F18 -> 16 | G19: =G21-G17-G18 -> -95 | H19: =H21-H17-H18 -> -1388 | I19: =0 -> 0 | J19: =0 -> 0 | K19: =0 -> 0 | L19: =0 -> 0 | M19: =0 -> 0
B20: FCI | D20: =D17+D18+D19 -> -11585 | E20: =E17+E18+E19 -> -6191 | F20: =F17+F18+F19 -> -8309 | G20: =G17+G18+G19 -> -14087 | H20: =H17+H18+H19 -> -61641 | I20: =I17+I18+I19 -> -52000 | J20: =J17+J18+J19 -> -58000 | K20: =K17+K18+K19 -> -38000 | ... M20: =M17+M18+M19 -> -36000
B21: memo: FCI reportado | D21: -11585 | E21: -6191 | F21: -8309 | G21: -14087 | H21: -61641
B23: FCF (FCO - capex liquido) | D23: =D14+D17 -> 3201 | E23: =E14+E17 -> -5451 | F23: =F14+F17 -> 387 | G23: =G14+G17 -> 3725 | H23: =H14+H17 -> 62305 | I23: =I14+I17 -> 142703.04 | J23: =J14+J17 -> 173453.27 | K23: =K14+K17 -> 127996.86 | ... M23: =M14+M17 -> 114281.5
B24: memo: FCF ajustado reportado pela empresa | D24: 3210 | E24: -5450 | F24: 386 | G24: 3720 | H24: 62310
B25: FCF / receita | D25: =D23/DRE!D5 -> 0.10407049 | E25: =E23/DRE!E5 -> -0.3507722 | F25: =F23/DRE!F5 -> 0.015411573 | G25: =G23/DRE!G5 -> 0.099657553 | H25: =H23/DRE!H5 -> 0.4677974 | I25: =I23/DRE!I5 -> 0.52301555 | J25: =J23/DRE!J5 -> 0.57717083 | K25: =K23/DRE!K5 -> 0.59975522 | ... M25: =M23/DRE!M5 -> 0.55238902
B27: (-) Dividendos | D27: -461 | E27: -504 | F27: -513 | G27: -522 | H27: -610 | I27: =-Suporte!I47 -> -779.9586 | J27: =-Suporte!J47 -> -914.81379 | K27: =-Suporte!K47 -> -945.59381 | L27: =-Suporte!L47 -> -878.96796 | M27: =-Suporte!M47 -> -802.39762
B28: (-) Recompras | D28: -2432 | E28: -425 | F28: -300 | G28: 0 | H28: -650 | I28: =-Suporte!I40 -> -85000 | J28: =-Suporte!J40 -> -160000 | K28: =-Suporte!K40 -> -120000 | L28: =-Suporte!L40 -> -85000 | M28: =-Suporte!M40 -> -100000
B29: (+/-) Captacao / amortizacao de divida | D29: -30 | E29: 5955 | F29: -898 | G29: -189 | H29: -10043 | I29: =Suporte!I28 -> -491 | J29: =Suporte!J28 -> 0 | K29: =Suporte!K28 -> 0 | L29: =Suporte!L28 -> 0 | M29: =Suporte!M28 -> -261
B30: (+) Depositos de clientes (SCAs) | D30: 0 | E30: 0 | F30: 0 | G30: 0 | H30: 12747 | I30: =0 -> 0 | J30: =0 -> 0 | K30: =0 -> 0 | L30: =0 -> 0 | M30: =0 -> 0
B31: Outros (hist.: residual, inclui withholding de RSUs) | D31: =D33-D27-D28-D29-D30 -> -57 | E31: =E33-E27-E28-E29-E30 -> -43 | F31: =F33-F27-F28-F29-F30 -> -131 | G31: =G33-G27-G28-G29-G30 -> -139 | H31: =H33-H27-H28-H29-H30 -> -814 | I31: =0 -> 0 | J31: =0 -> 0 | K31: =0 -> 0 | L31: =0 -> 0 | M31: =0 -> 0
B32: FCF ao acionista / financiamento (FCF - div - recompras +/- divida + outros) | D32: =D23+D27+D28+D29+D30+D31 -> 221 | E32: =E23+E27+E28+E29+E30+E31 -> -468 | F32: =F23+F27+F28+F29+F30+F31 -> -1455 | G32: =G23+G27+G28+G29+G30+G31 -> 2875 | H32: =H23+H27+H28+H29+H30+H31 -> 62935 | I32: =I23+I27+I28+I29+I30+I31 -> 56432.078 | J32: =J23+J27+J28+J29+J30+J31 -> 12538.459 | K32: =K23+K27+K28+K29+K30+K31 -> 7051.2683 | ... M32: =M23+M27+M28+M29+M30+M31 -> 13218.099
B33: memo: fluxo de financiamento reportado | D33: -2980 | E33: 4983 | F33: -1842 | G33: -850 | H33: 630
B34: Efeito cambial | D34: -106 | E34: -34 | F34: 40 | G34: 6 | H34: 81 | I34: =0 -> 0 | J34: =0 -> 0 | K34: =0 -> 0 | L34: =0 -> 0 | M34: =0 -> 0
B35: Variacao de caixa | D35: =D14+D20+D27+D28+D29+D30+D31+D34 -> 510 | E35: =E14+E20+E27+E28+E29+E30+E31+E34 -> 317 | F35: =F14+F20+F27+F28+F29+F30+F31+F34 -> -1604 | G35: =G14+G20+G27+G28+G29+G30+G31+G34 -> 2594 | H35: =H14+H20+H27+H28+H29+H30+H31+H34 -> 28745 | I35: =I14+I20+I27+I28+I29+I30+I31+I34 -> 56432.078 | J35: =J14+J20+J27+J28+J29+J30+J31+J34 -> 12538.459 | K35: =K14+K20+K27+K28+K29+K30+K31+K34 -> 7051.2683 | ... M35: =M14+M20+M27+M28+M29+M30+M31+M34 -> 13218.099
B36: memo: var. caixa e restrito reportada | C36: cx+restr. | D36: 510 | E36: 317 | F36: -1604 | G36: 2594 | H36: 28745
B37: Caixa e aplicacoes inicial (BP) | E37: =BP!D5 -> 10978 | F37: =BP!E5 -> 10438 | G37: =BP!F5 -> 9152 | H37: =BP!G5 -> 11936 | I37: =BP!H5 -> 73453 | J37: =BP!I5 -> 129885.08 | K37: =BP!J5 -> 142423.54 | L37: =BP!K5 -> 149474.81 | M37: =BP!L5 -> 157075.24
B38: Caixa e aplicacoes final -> BP | E38: =E37+E35 -> 11295 | F38: =F37+F35 -> 8834 | G38: =G37+G35 -> 11746 | H38: =H37+H35 -> 40681 | I38: =I37+I35 -> 129885.08 | J38: =J37+J35 -> 142423.54 | K38: =K37+K35 -> 149474.81 | L38: =L37+L35 -> 157075.24 | M38: =M37+M35 -> 170293.33
B39: Check: caixa BP - caixa FC (hist.: var. calc. - reportada) | D39: =D35-D36 -> 0 | E39: =E35-E36 -> 0 | F39: =F35-F36 -> 0 | G39: =G35-G36 -> 0 | H39: =H35-H36 -> 0 | I39: =BP!I5-I38 -> 0 | J39: =BP!J5-J38 -> 0 | K39: =BP!K5-K38 -> 0 | L39: =BP!L5-L38 -> 0 | M39: =BP!M5-M38 -> 0
B40: Check caixa | D40: =IF(ABS(D39)<0.5,"ok","ERRO") -> ok | E40: =IF(ABS(E39)<0.5,"ok","ERRO") -> ok | F40: =IF(ABS(F39)<0.5,"ok","ERRO") -> ok | G40: =IF(ABS(G39)<0.5,"ok","ERRO") -> ok | H40: =IF(ABS(H39)<0.5,"ok","ERRO") -> ok | I40: =IF(ABS(I39)<0.5,"ok","ERRO") -> ok | J40: =IF(ABS(J39)<0.5,"ok","ERRO") -> ok | K40: =IF(ABS(K39)<0.5,"ok","ERRO") -> ok | ... M40: =IF(ABS(M39)<0.5,"ok","ERRO") -> ok
B41: Check caixa (todos os anos) | D41: =IF(COUNTIF(D40:M40,"ok")=10,"ok","ERRO") -> ok
B43: FCF yield (FCF / mkt cap atual) | D43: =D23/Multiplos!$D$7 -> 0.0027107707 | E43: =E23/Multiplos!$D$7 -> -0.0046161858 | F43: =F23/Multiplos!$D$7 -> 0.00032773141 | G43: =G23/Multiplos!$D$7 -> 0.0031545207 | H43: =H23/Multiplos!$D$7 -> 0.052763063 | I43: =I23/Multiplos!$D$7 -> 0.12084824 | J43: =J23/Multiplos!$D$7 -> 0.14688911 | K43: =K23/Multiplos!$D$7 -> 0.10839429 | ... M43: =M23/Multiplos!$D$7 -> 0.096779421
B44: FCF por acao (US$) | D44: =D23/DRE!D30 -> 2.8529412 | E44: =E23/DRE!E30 -> -4.9871912 | F44: =F23/DRE!F30 -> 0.34615385 | G44: =G23/DRE!G30 -> 3.3111111 | H44: =H23/DRE!H30 -> 54.510061 | I44: =I23/DRE!I30 -> 128.00044 | J44: =J23/DRE!J30 -> 171.11548 | K44: =K23/DRE!K30 -> 144.15052 | ... M44: =M23/DRE!M30 -> 168.81187

Sheet Suporte
B1: Suporte - imobilizado, capital de giro, divida e acoes
B2: projecoes leem a linha 'Selecionado' da aba Premissas; receita de juros sobre o caixa inicial (evita circularidade)
B4: US$ mn, exceto onde indicado | D4: FY22A | E4: FY23A | F4: FY24A | G4: FY25A | H4: FY26A | I4: FY27E | J4: FY28E | K4: FY29E | L4: FY30E | M4: FY31E
B5: Ano fiscal (num.) | D5: 2022 | E5: 2023 | F5: 2024 | G5: 2025 | H5: 2026 | I5: 2027 | J5: 2028 | K5: 2029 | L5: 2030 | M5: 2031
B7: (a) Imobilizado
B8: PP&E liq. inicial | C8: FY22 n.d. | E8: =D11 -> 38549 | F8: =E11 -> 37928 | G8: =F11 -> 39749 | H8: =G11 -> 46590 | I8: =H11 -> 63310 | J8: =I11 -> 102837.93 | K8: =J11 -> 143869.67 | L8: =K11 -> 158850.52 | M8: =L11 -> 161845.94
B9: (+) Capex liquido | D9: =-FC!D17 -> 11980 | E9: =-FC!E17 -> 7010 | F9: =-FC!F17 -> 8120 | G9: =-FC!G17 -> 13800 | H9: =-FC!H17 -> 27370 | I9: =Premissas!I71 -> 52000 | J9: =Premissas!J71 -> 58000 | K9: =Premissas!K71 -> 38000 | L9: =Premissas!L71 -> 30000 | M9: =Premissas!M71 -> 36000
B10: (-) D&A | D10: =-DRE!D15 -> -7116 | E10: =-DRE!E15 -> -7756 | F10: =-DRE!F15 -> -7780 | G10: =-DRE!G15 -> -8352 | H10: =-DRE!H15 -> -9503 | I10: =-I8*Premissas!I77 -> -12472.07 | J10: =-J8*Premissas!J77 -> -16968.258 | K10: =-K8*Premissas!K77 -> -23019.147 | L10: =-L8*Premissas!L77 -> -27004.589 | M10: =-M8*Premissas!M77 -> -29132.268
B11: PP&E liq. final | D11: =BP!D13 -> 38549 | E11: =BP!E13 -> 37928 | F11: =BP!F13 -> 39749 | G11: =BP!G13 -> 46590 | H11: =BP!H13 -> 63310 | I11: =I8+I9+I10 -> 102837.93 | J11: =J8+J9+J10 -> 143869.67 | K11: =K8+K9+K10 -> 158850.52 | L11: =L8+L9+L10 -> 161845.94 | M11: =M8+M9+M10 -> 168713.67
B12: D&A / PP&E liq. inicial | E12: =-E10/E8 -> 0.20119847 | F12: =-F10/F8 -> 0.2051255 | G12: =-G10/G8 -> 0.21011849 | H12: =-H10/H8 -> 0.20397081 | I12: =-I10/I8 -> 0.197 | J12: =-J10/J8 -> 0.165 | K12: =-K10/K8 -> 0.16 | L12: =-L10/L8 -> 0.17 | M12: =-M10/M8 -> 0.18
B13: Capex / receita | D13: =D9/DRE!D5 -> 0.38949216 | E13: =E9/DRE!E5 -> 0.45109395 | F13: =F9/DRE!F5 -> 0.32336426 | G13: =G9/DRE!G5 -> 0.36920113 | H13: =H9/DRE!H5 -> 0.20549899 | I13: =I9/DRE!I5 -> 0.19058325 | J13: =J9/DRE!J5 -> 0.19299669 | K13: =K9/DRE!K5 -> 0.1780567 | ... M13: =M9/DRE!M5 -> 0.17400896
B14: Capex / D&A (x) | D14: =-D9/D10 -> 1.6835301 | E14: =-E9/E10 -> 0.9038164 | F14: =-F9/F10 -> 1.0437018 | G14: =-G9/G10 -> 1.6522989 | H14: =-H9/H10 -> 2.8801431 | I14: =-I9/I10 -> 4.1693159 | J14: =-J9/J10 -> 3.4181469 | K14: =-K9/K10 -> 1.6507996 | ... M14: =-M9/M10 -> 1.2357431
B16: (b) Capital de giro
B17: DSO (dias) = CR / receita x 365 | C17: hist: calc. | D17: =D20/DRE!D5*365 -> 60.876845 | E17: =E20/DRE!E5*365 -> 57.380631 | F17: =F20/DRE!F5*365 -> 96.152085 | G17: =G20/DRE!G5*365 -> 90.473674 | H17: =H20/DRE!H5*365 -> 99.197413 | I17: =Premissas!I89 -> 71 | J17: =Premissas!J89 -> 64 | K17: =Premissas!K89 -> 56 | L17: =Premissas!L89 -> 55 | M17: =Premissas!M89 -> 60
B18: DIO (dias) = estoques / COGS x 365 | D18: =D21/(-DRE!D7)*365 -> 144.24644 | E18: =E21/(-DRE!E7)*365 -> 180.54111 | F18: =F21/(-DRE!F7)*365 -> 166.13883 | G18: =G21/(-DRE!G7)*365 -> 135.50655 | H18: =H21/(-DRE!H7)*365 -> 147.39838 | I18: =Premissas!I95 -> 131 | J18: =Premissas!J95 -> 128 | K18: =Premissas!K95 -> 158 | L18: =Premissas!L95 -> 165 | M18: =Premissas!M95 -> 142
B19: DPO (dias) = fornecedores e provisoes / COGS x 365 | D19: =D22/(-DRE!D7)*365 -> 131.84164 | E19: =E22/(-DRE!E7)*365 -> 85.201109 | F19: =F22/(-DRE!F7)*365 -> 136.63632 | G19: =G22/(-DRE!G7)*365 -> 156.49345 | H19: =H22/(-DRE!H7)*365 -> 321.24377 | I19: =Premissas!I101 -> 284 | J19: =Premissas!J101 -> 250 | K19: =Premissas!K101 -> 158 | L19: =Premissas!L101 -> 138 | M19: =Premissas!M101 -> 150
B20: Contas a receber | D20: =BP!D9 -> 5130 | E20: =BP!E9 -> 2443 | F20: =BP!F9 -> 6615 | G20: =BP!G9 -> 9265 | H20: =BP!H9 -> 36197 | I20: =DRE!I5*I17/365 -> 53074.278 | J20: =DRE!J5*J17/365 -> 52694.494 | K20: =DRE!K5*K17/365 -> 32743.149 | L20: =DRE!L5*L17/365 -> 25119.995 | M20: =DRE!M5*M17/365 -> 34008.64
B21: Estoques | D21: =BP!D10 -> 6663 | E21: =BP!E10 -> 8387 | F21: =BP!F10 -> 8875 | G21: =BP!G10 -> 8355 | H21: =BP!H10 -> 10372 | I21: =-DRE!I7*I18/365 -> 12919.83 | J21: =-DRE!J7*J18/365 -> 14577.35 | K21: =-DRE!K7*K18/365 -> 21282.142 | L21: =-DRE!L7*L18/365 -> 23885.825 | M21: =-DRE!M7*M18/365 -> 21843.05
B22: Fornecedores e provisoes | D22: =BP!D18 -> 6090 | E22: =BP!E18 -> 3958 | F22: =BP!F18 -> 7299 | G22: =BP!G18 -> 9649 | H22: =BP!H18 -> 22605 | I22: =-DRE!I7*I19/365 -> 28009.403 | J22: =-DRE!J7*J19/365 -> 28471.387 | K22: =-DRE!K7*K19/365 -> 21282.142 | L22: =-DRE!L7*L19/365 -> 19977.235 | M22: =-DRE!M7*M19/365 -> 23073.644
B23: NWC operacional (CR + estoques - fornecedores) | D23: =D20+D21-D22 -> 5703 | E23: =E20+E21-E22 -> 6872 | F23: =F20+F21-F22 -> 8191 | G23: =G20+G21-G22 -> 7971 | H23: =H20+H21-H22 -> 23964 | I23: =I20+I21-I22 -> 37984.705 | J23: =J20+J21-J22 -> 38800.457 | K23: =K20+K21-K22 -> 32743.149 | ... M23: =M20+M21-M22 -> 32778.046
B24: Variacao de NWC (aumento = uso de caixa) | E24: =E23-D23 -> 1169 | F24: =F23-E23 -> 1319 | G24: =G23-F23 -> -220 | H24: =H23-G23 -> 15993 | I24: =I23-H23 -> 14020.705 | J24: =J23-I23 -> 815.75155 | K24: =K23-J23 -> -6057.3077 | L24: =L23-K23 -> -3714.5646 | M24: =M23-L23 -> 3749.4611
B26: (c) Divida e resultado financeiro
B27: Divida total inicial | I27: =H29 -> 5179 | J27: =I29 -> 4688 | K27: =J29 -> 4688 | L27: =K29 -> 4688 | M27: =L29 -> 4688
B28: (-) Amortizacao programada (vencimentos) | C28: tabela (e) | I28: =-SUMPRODUCT(($D$51:$D$61=I$5)*$E$51:$E$61) -> -491 | J28: =-SUMPRODUCT(($D$51:$D$61=J$5)*$E$51:$E$61) -> 0 | K28: =-SUMPRODUCT(($D$51:$D$61=K$5)*$E$51:$E$61) -> 0 | L28: =-SUMPRODUCT(($D$51:$D$61=L$5)*$E$51:$E$61) -> 0 | M28: =-SUMPRODUCT(($D$51:$D$61=M$5)*$E$51:$E$61) -> -261
B29: Divida total final | H29: =BP!H19+BP!H22 -> 5179 | I29: =I27+I28 -> 4688 | J29: =J27+J28 -> 4688 | K29: =K27+K28 -> 4688 | L29: =L27+L28 -> 4688 | M29: =M27+M28 -> 4427
B30: da qual curto prazo (vence no ano seguinte) | I30: =SUMPRODUCT(($D$51:$D$61=I$5+1)*$E$51:$E$61) -> 0 | J30: =SUMPRODUCT(($D$51:$D$61=J$5+1)*$E$51:$E$61) -> 0 | K30: =SUMPRODUCT(($D$51:$D$61=K$5+1)*$E$51:$E$61) -> 0 | L30: =SUMPRODUCT(($D$51:$D$61=L$5+1)*$E$51:$E$61) -> 261 | M30: =SUMPRODUCT(($D$51:$D$61=M$5+1)*$E$51:$E$61) -> 1066
B31: da qual longo prazo | I31: =I29-I30 -> 4688 | J31: =J29-J30 -> 4688 | K31: =K29-K30 -> 4688 | L31: =L29-L30 -> 4427 | M31: =M29-M30 -> 3361
B32: Custo medio da divida | I32: =Premissas!I125 -> 0.045 | J32: =Premissas!J125 -> 0.045 | K32: =Premissas!K125 -> 0.045 | L32: =Premissas!L125 -> 0.045 | M32: =Premissas!M125 -> 0.045
B33: Despesa de juros = saldo medio x custo medio | I33: =-(I27+I29)/2*I32 -> -222.0075 | J33: =-(J27+J29)/2*J32 -> -210.96 | K33: =-(K27+K29)/2*K32 -> -210.96 | L33: =-(L27+L29)/2*L32 -> -210.96 | M33: =-(M27+M29)/2*M32 -> -205.0875
B34: Caixa e aplicacoes inicial (BP ano anterior) | I34: =BP!H5 -> 73453 | J34: =BP!I5 -> 129885.08 | K34: =BP!J5 -> 142423.54 | L34: =BP!K5 -> 149474.81 | M34: =BP!L5 -> 157075.24
B35: Yield do caixa | I35: =Premissas!I119 -> 0.043 | J35: =Premissas!J119 -> 0.041 | K35: =Premissas!K119 -> 0.038 | L35: =Premissas!L119 -> 0.036 | M35: =Premissas!M119 -> 0.036
B36: Receita de juros = caixa inicial x yield | C36: cx inicial | I36: =I34*I35 -> 3158.479 | J36: =J34*J35 -> 5325.2882 | K36: =K34*K35 -> 5412.0944 | L36: =L34*L35 -> 5381.093 | M36: =M34*M35 -> 5654.7085
B38: (d) Acoes e dividendos
B39: Acoes diluidas - inicio (mn) | I39: =H44 -> 1150 | J39: =I44 -> 1079.7273 | K39: =J44 -> 947.59684 | L39: =K44 -> 828.28105 | M39: =L44 -> 729.03105
B40: Recompras (US$ mn) | I40: =Premissas!I107 -> 85000 | J40: =Premissas!J107 -> 160000 | K40: =Premissas!K107 -> 120000 | L40: =Premissas!L107 -> 85000 | M40: =Premissas!M107 -> 100000
B41: Preco medio de recompra (US$) | I41: =Premissas!I131 -> 1100 | J41: =Premissas!J131 -> 1150 | K41: =Premissas!K131 -> 950 | L41: =Premissas!L131 -> 800 | M41: =Premissas!M131 -> 900
B42: (-) Acoes recompradas (mn) | I42: =-I40/I41 -> -77.272727 | J42: =-J40/J41 -> -139.13043 | K42: =-K40/K41 -> -126.31579 | L42: =-L40/L41 -> -106.25 | M42: =-M40/M41 -> -111.11111
B43: (+) Diluicao de SBC (mn) | I43: =Premissas!I137 -> 7 | J43: =Premissas!J137 -> 7 | K43: =Premissas!K137 -> 7 | L43: =Premissas!L137 -> 7 | M43: =Premissas!M137 -> 7
B44: Acoes diluidas - fim (mn) | C44: guia 1T27 | H44: 1150 | I44: =I39+I42+I43 -> 1079.7273 | J44: =J39+J42+J43 -> 947.59684 | K44: =K39+K42+K43 -> 828.28105 | L44: =L39+L42+L43 -> 729.03105 | M44: =M39+M42+M43 -> 624.91994
B45: Acoes diluidas - media (mn) -> DRE | I45: =(I39+I44)/2 -> 1114.8636 | J45: =(J39+J44)/2 -> 1013.6621 | K45: =(K39+K44)/2 -> 887.93894 | L45: =(L39+L44)/2 -> 778.65605 | M45: =(M39+M44)/2 -> 676.97549
B46: DPS (US$) | D46: =DRE!D42 -> 0.415 | E46: =DRE!E42 -> 0.46 | F46: =DRE!F42 -> 0.46 | G46: =DRE!G42 -> 0.46 | H46: =DRE!H42 -> 0.53 | I46: =DRE!I42 -> 0.6996 | J46: =DRE!J42 -> 0.902484 | K46: =DRE!K42 -> 1.0649311 | ... M46: =DRE!M42 -> 1.1852683
B47: Dividendos pagos (US$ mn) = DPS x acoes medias | D47: =-FC!D27 -> 461 | E47: =-FC!E27 -> 504 | F47: =-FC!F27 -> 513 | G47: =-FC!G27 -> 522 | H47: =-FC!H27 -> 610 | I47: =I46*I45 -> 779.9586 | J47: =J46*J45 -> 914.81379 | K47: =K46*K45 -> 945.59381 | L47: =L46*L45 -> 878.96796 | M47: =M46*M45 -> 802.39762
B49: (e) Divida por instrumento - 10-Q 28/mai/26 (ultimo detalhe disponivel; 10-K FY26 pendente)
B50: Instrumento | C50: Cupom | D50: Venc. (FY) | E50: Saldo 28/mai/26 | F50: Est.? | G50: Nota
B51: 2031 Notes (5.300% Senior Notes due 2031) | C51: 0.053 | D51: 2031 | E51: 261 | F51: est. | G51: Original principal inferred from tender offer ($5.4bn across 6 series); remaining principal approximated by ca
B52: 2032 Green Bonds (2.703% due 2032) | C52: 0.02703 | D52: 2032 | E52: 996 | G52: Issued Nov-2021 (FY22) - not tendered
B53: 2032 Notes (5.650% Senior Notes due 2032) | C53: 0.0565 | D53: 2032 | E53: 70 | F53: est. | G53: Issued FY25; mostly tendered Apr-2026
B54: 2033 A Notes (5.875% due 2033) | C54: 0.05875 | D54: 2033 | E54: 175 | F54: est. | G54: Original principal inferred (tender total 5.4bn); carrying 746 at Aug-25 suggests prior partial repurchases
B55: 2033 B Notes (5.875% due 2033) | C55: 0.05875 | D55: 2033 | E55: 213 | F55: est. | G55: $750mn outstanding pre-tender per expiration release; ~574mn tendered (carrying 892 at Aug-25 per 10-Q table -
B56: 2035 A Notes (5.800% due 2035) | C56: 0.058 | D56: 2035 | E56: 135 | F56: est. | G56: Issued Jan-2025 (proceeds ~992); ~863mn tendered
B57: 2035 B Notes (6.050% due 2035) | C57: 0.0605 | D57: 2035 | E57: 219 | F57: est. | G57: ~1.03bn tendered
B58: 2041 Notes (3.366% due 2041) | C58: 0.03366 | D58: 2041 | E58: 497 | G58: Issued Nov-2021; not tendered
B59: 2051 Notes (3.477% due 2051) | C59: 0.03477 | D59: 2051 | E59: 486 | F59: est. | G59: $10mn principal repurchased Jan-2026 for $7mn cash
B60: Finance lease obligations | C60: 0.0472 | D60: varios | E60: 2670 | F60: est. | G60: Effective rate 4.72%; 582 current / 2,088 long-term at 2026-05-28; amortizing through FY26 Q4
B61: Parcela corrente em 03/set/26 (leases e outros; vence no FY27) | D61: 2027 | E61: =BP!$H$19 -> 491 | G61: Divida de curto prazo do balanco de 03/set/26 (press release 4T26)
B62: Soma da tabela (mai/26 + parcela corrente) | E62: =SUM(E51:E61) -> 6213
B63: Divida total em 03/set/26 (BP) | E63: =BP!$H$19+BP!$H$22 -> 5179
B64: Diferenca (recompras do 4T26 ~0,5 bi, amortizacao de leases; detalhe so no 10-K) | E64: =E63-E62 -> -1034
B65: Cupom medio ponderado (notas + leases, mai/26) | E65: =SUMPRODUCT(C51:C60,E51:E60)/SUM(E51:E60) -> 0.043382667
B66: Rating: Moody's Baa1 estavel (~ago/26; Baa2 em jan/26) | S&P BBB positivo (mai/26) | Fitch BBB (dez/25)

Sheet DCF
B1: DCF - FCFF FY27E-FY31E + ano normalizado (mid-cycle)
B2: valuation em 07/out/26; preco-alvo 12m = valor justo x (1+Ke) - DPS 12m; WACC e g da aba Premissas
B4: US$ mn, exceto onde indicado | D4: FY22A | E4: FY23A | F4: FY24A | G4: FY25A | H4: FY26A | I4: FY27E | J4: FY28E | K4: FY29E | L4: FY30E | M4: FY31E | N4: Normalizado
B5: n (ano de projecao) | I5: 1 | J5: 2 | K5: 3 | L5: 4 | M5: 5
B6: Rec. liq. | I6: =DRE!I5 -> 272846.64 | J6: =DRE!J5 -> 300523.29 | K6: =DRE!K5 -> 213415.17 | L6: =DRE!L5 -> 166705.42 | M6: =DRE!M5 -> 206885.89 | N6: =M6*Premissas!$I$149 -> 196541.6
B7: MB | I7: =DRE!I9 -> 0.86806508 | J7: =DRE!J9 -> 0.86168052 | K7: =DRE!K9 -> 0.76963004 | L7: =DRE!L9 -> 0.68304367 | M7: =DRE!M9 -> 0.72861433 | N7: =Premissas!$I$144 -> 0.62
B8: Lucro bruto | I8: =I6*I7 -> 236848.64 | J8: =J6*J7 -> 258955.06 | K8: =K6*K7 -> 164250.73 | L8: =L6*L7 -> 113867.08 | M8: =M6*M7 -> 150740.03 | N8: =N6*N7 -> 121855.79
B9: Desp. op. (R&D + SG&A + outros) | I9: =DRE!I10+DRE!I11+DRE!I12 -> -9891.75 | J9: =DRE!J10+DRE!J11+DRE!J12 -> -11080.327 | K9: =DRE!K10+DRE!K11+DRE!K12 -> -11306.626 | L9: =DRE!L10+DRE!L11+DRE!L12 -> -11001.706 | M9: =DRE!M10+DRE!M11+DRE!M12 -> -11636.858 | N9: =-N6*Premissas!$I$154 -> -14150.995
B10: EBIT | I10: =I8+I9 -> 226956.89 | J10: =J8+J9 -> 247874.73 | K10: =K8+K9 -> 152944.1 | L10: =L8+L9 -> 102865.38 | M10: =M8+M9 -> 139103.17 | N10: =N8+N9 -> 107704.8
B11: mg EBIT | I11: =I10/I6 -> 0.83181119 | J11: =J10/J6 -> 0.8248104 | K11: =K10/K6 -> 0.71665056 | L11: =L10/L6 -> 0.61704878 | M11: =M10/M6 -> 0.67236662 | N11: =N10/N6 -> 0.548
B12: Aliquota | I12: =Premissas!I83 -> 0.155 | J12: =Premissas!J83 -> 0.158 | K12: =Premissas!K83 -> 0.15 | L12: =Premissas!L83 -> 0.165 | M12: =Premissas!M83 -> 0.155 | N12: =Premissas!$I$169 -> 0.155
B13: NOPAT = EBIT x (1 - t) | I13: =I10*(1-I12) -> 191778.57 | J13: =J10*(1-J12) -> 208710.52 | K13: =K10*(1-K12) -> 130002.49 | L13: =L10*(1-L12) -> 85892.59 | M13: =M10*(1-M12) -> 117542.18 | N13: =N10*(1-N12) -> 91010.553
B14: (+) D&A | I14: =-Suporte!I10 -> 12472.07 | J14: =-Suporte!J10 -> 16968.258 | K14: =-Suporte!K10 -> 23019.147 | L14: =-Suporte!L10 -> 27004.589 | M14: =-Suporte!M10 -> 29132.268 | N14: =N6*Premissas!$I$164 -> 32429.364
B15: (-) Capex liquido | I15: =-Suporte!I9 -> -52000 | J15: =-Suporte!J9 -> -58000 | K15: =-Suporte!K9 -> -38000 | L15: =-Suporte!L9 -> -30000 | M15: =-Suporte!M9 -> -36000 | N15: =-N6*Premissas!$I$159 -> -47169.984
B16: (-) Variacao de NWC | I16: =-Suporte!I24 -> -14020.705 | J16: =-Suporte!J24 -> -815.75155 | K16: =-Suporte!K24 -> 6057.3077 | L16: =-Suporte!L24 -> 3714.5646 | M16: =-Suporte!M24 -> -3749.4611 | N16: =-(N6-M6)*Premissas!$I$174 -> 1551.6442
B17: FCFF | I17: =I13+I14+I15+I16 -> 138229.94 | J17: =J13+J14+J15+J16 -> 166863.03 | K17: =K13+K14+K15+K16 -> 121078.94 | L17: =L13+L14+L15+L16 -> 86611.744 | M17: =M13+M14+M15+M16 -> 106924.98 | N17: =N13+N14+N15+N16 -> 77821.577
B18: FCFF / receita | I18: =I17/I6 -> 0.50662136 | J18: =J17/J6 -> 0.55524161 | K18: =K17/K6 -> 0.5673399 | L18: =L17/L6 -> 0.51954965 | M18: =M17/M6 -> 0.51683072 | N18: =N17/N6 -> 0.39595474
B19: Periodo de desconto (t) | I19: =I5-$I$58/2 -> 0.5 | J19: =J5-$I$58/2 -> 1.5 | K19: =K5-$I$58/2 -> 2.5 | L19: =L5-$I$58/2 -> 3.5 | M19: =M5-$I$58/2 -> 4.5
B20: Fator de desconto | I20: =1/(1+$I$56)^I19 -> 0.94124429 | J20: =1/(1+$I$56)^J19 -> 0.83388673 | K20: =1/(1+$I$56)^K19 -> 0.73877429 | L20: =1/(1+$I$56)^L19 -> 0.65451029 | M20: =1/(1+$I$56)^M19 -> 0.57985738
B21: VP do FCFF | I21: =I17*I20 -> 130108.14 | J21: =J17*J20 -> 139144.87 | K21: =K17*K20 -> 89450.008 | L21: =L17*L20 -> 56688.278 | M21: =M17*M20 -> 62001.241
B23: Valuation
B24: Soma VP FCFF FY27E-FY31E | I24: =SUM(I21:M21) -> 477392.53
B25: Valor terminal (TV) = FCFF norm. x (1+g) / (WACC - g) | I25: =N17*(1+I57)/(I56-I57) -> 811761.42
B26: VP do TV | I26: =I25*M20 -> 470705.85
B27: EV | I27: =I24+I26 -> 948098.38
B28: TV % EV | I28: =I26/I27 -> 0.49647363
B29: (+) Caixa e aplicacoes FY26A | I29: =BP!$H$5 -> 73453
B30: (-) Divida FY26A | I30: =-(BP!$H$19+BP!$H$22) -> -5179
B31: Equity value | I31: =I27+I29+I30 -> 1016372.4
B32: Acoes diluidas (mn) | C32: guia 1T27 | I32: =Suporte!$H$44 -> 1150
B33: Valor justo por acao hoje (US$) | I33: =I31/I32 -> 883.80207
B34: Ke (12m) | I34: =I51 -> 0.12914
B35: DPS 12m (FY27E) | I35: =DRE!$I$42 -> 0.6996
B36: Preco-alvo 12m (US$) | I36: =I33*(1+I34)-I35 -> 997.23667
B37: Preco atual (US$) | I37: =Premissas!$I$203 -> 1045.56
B38: Upside | I38: =I36/I37-1 -> -0.046217651
B40: Multiplos implicitos no preco-alvo
B41: EV implicito (PT x acoes - caixa + divida) | I41: =I36*I32-I29-I30 -> 1078548.2
B42: EV/EBITDA FY27E | I42: =I41/DRE!$I$16 -> 4.5046688
B43: EV/EBITDA FY28E | I43: =I41/DRE!$J$16 -> 4.072406
B44: P/E FY27E (non-GAAP) | I44: =I36/DRE!$I$39 -> 5.6740134
B45: P/E FY28E (non-GAAP) | I45: =I36/DRE!$J$39 -> 4.7029937
B47: WACC (link Premissas)
B48: Rf | I48: =Premissas!$I$177 -> 0.0527
B49: Beta | I49: =Premissas!$I$182 -> 1.82
B50: ERP | I50: =Premissas!$I$183 -> 0.042
B51: Ke | I51: =Premissas!$I$184 -> 0.12914
B52: Kd pre-IR | I52: =Premissas!$I$185 -> 0.059
B53: Aliquota | I53: =Premissas!$I$186 -> 0.155
B54: Peso equity | I54: =Premissas!$I$189 -> 0.995
B55: Peso divida | I55: =Premissas!$I$188 -> 0.005
B56: WACC | I56: =Premissas!$I$190 -> 0.12874357
B57: g terminal | I57: =Premissas!$I$195 -> 0.03
B58: Meio de ano (1/0) | I58: =Premissas!$I$196 -> 1
B60: Sensibilidade 1: preco-alvo (US$) - WACC (linhas) x g terminal (colunas)
B61: passo WACC | C61: 0.005 | D61: passo g | E61: 0.005 | F61: passo MB | G61: 0.02
C63: WACC \ g | D63: =$I$57+(-2)*$E$61 -> 0.02 | E63: =$I$57+(-1)*$E$61 -> 0.025 | F63: =$I$57+(0)*$E$61 -> 0.03 | G63: =$I$57+(1)*$E$61 -> 0.035 | H63: =$I$57+(2)*$E$61 -> 0.04
C64: =$I$56+(-2)*$C$61 -> 0.11874358 | D64: =((SUMPRODUCT($I$17:$M$17,1/(1+$C64)^$I$19:$M$19)+$N$17*(1+D$63)/($C64-D$63)/(1+$C64)^$M$19+$I$29+$I$30)/$I$32)*(1+$I$51)-$I$35 -> 1020.0789 | E64: =((SUMPRODUCT($I$17:$M$17,1/(1+$C64)^$I$19:$M$19)+$N$17*(1+E$63)/($C64-E$63)/(1+$C64)^$M$19+$I$29+$I$30)/$I$32)*(1+$I$51)-$I$35 -> 1047.9473 | F64: =((SUMPRODUCT($I$17:$M$17,1/(1+$C64)^$I$19:$M$19)+$N$17*(1+F$63)/($C64-F$63)/(1+$C64)^$M$19+$I$29+$I$30)/$I$32)*(1+$I$51)-$I$35 -> 1078.9561 | G64: =((SUMPRODUCT($I$17:$M$17,1/(1+$C64)^$I$19:$M$19)+$N$17*(1+G$63)/($C64-G$63)/(1+$C64)^$M$19+$I$29+$I$30)/$I$32)*(1+$I$51)-$I$35 -> 1113.6677 | H64: =((SUMPRODUCT($I$17:$M$17,1/(1+$C64)^$I$19:$M$19)+$N$17*(1+H$63)/($C64-H$63)/(1+$C64)^$M$19+$I$29+$I$30)/$I$32)*(1+$I$51)-$I$35 -> 1152.7875
C65: =$I$56+(-1)*$C$61 -> 0.12374357 | D65: =((SUMPRODUCT($I$17:$M$17,1/(1+$C65)^$I$19:$M$19)+$N$17*(1+D$63)/($C65-D$63)/(1+$C65)^$M$19+$I$29+$I$30)/$I$32)*(1+$I$51)-$I$35 -> 983.75868 | E65: =((SUMPRODUCT($I$17:$M$17,1/(1+$C65)^$I$19:$M$19)+$N$17*(1+E$63)/($C65-E$63)/(1+$C65)^$M$19+$I$29+$I$30)/$I$32)*(1+$I$51)-$I$35 -> 1008.5509 | F65: =((SUMPRODUCT($I$17:$M$17,1/(1+$C65)^$I$19:$M$19)+$N$17*(1+F$63)/($C65-F$63)/(1+$C65)^$M$19+$I$29+$I$30)/$I$32)*(1+$I$51)-$I$35 -> 1035.9877 | G65: =((SUMPRODUCT($I$17:$M$17,1/(1+$C65)^$I$19:$M$19)+$N$17*(1+G$63)/($C65-G$63)/(1+$C65)^$M$19+$I$29+$I$30)/$I$32)*(1+$I$51)-$I$35 -> 1066.5163 | H65: =((SUMPRODUCT($I$17:$M$17,1/(1+$C65)^$I$19:$M$19)+$N$17*(1+H$63)/($C65-H$63)/(1+$C65)^$M$19+$I$29+$I$30)/$I$32)*(1+$I$51)-$I$35 -> 1100.6903
C66: =$I$56+(0)*$C$61 -> 0.12874357 | D66: =((SUMPRODUCT($I$17:$M$17,1/(1+$C66)^$I$19:$M$19)+$N$17*(1+D$63)/($C66-D$63)/(1+$C66)^$M$19+$I$29+$I$30)/$I$32)*(1+$I$51)-$I$35 -> 950.66155 | E66: =((SUMPRODUCT($I$17:$M$17,1/(1+$C66)^$I$19:$M$19)+$N$17*(1+E$63)/($C66-E$63)/(1+$C66)^$M$19+$I$29+$I$30)/$I$32)*(1+$I$51)-$I$35 -> 972.82675 | F66: =((SUMPRODUCT($I$17:$M$17,1/(1+$C66)^$I$19:$M$19)+$N$17*(1+F$63)/($C66-F$63)/(1+$C66)^$M$19+$I$29+$I$30)/$I$32)*(1+$I$51)-$I$35 -> 997.23667 | G66: =((SUMPRODUCT($I$17:$M$17,1/(1+$C66)^$I$19:$M$19)+$N$17*(1+G$63)/($C66-G$63)/(1+$C66)^$M$19+$I$29+$I$30)/$I$32)*(1+$I$51)-$I$35 -> 1024.2505 | H66: =((SUMPRODUCT($I$17:$M$17,1/(1+$C66)^$I$19:$M$19)+$N$17*(1+H$63)/($C66-H$63)/(1+$C66)^$M$19+$I$29+$I$30)/$I$32)*(1+$I$51)-$I$35 -> 1054.3084
C67: =$I$56+(1)*$C$61 -> 0.13374358 | D67: =((SUMPRODUCT($I$17:$M$17,1/(1+$C67)^$I$19:$M$19)+$N$17*(1+D$63)/($C67-D$63)/(1+$C67)^$M$19+$I$29+$I$30)/$I$32)*(1+$I$51)-$I$35 -> 920.36496 | E67: =((SUMPRODUCT($I$17:$M$17,1/(1+$C67)^$I$19:$M$19)+$N$17*(1+E$63)/($C67-E$63)/(1+$C67)^$M$19+$I$29+$I$30)/$I$32)*(1+$I$51)-$I$35 -> 940.27112 | F67: =((SUMPRODUCT($I$17:$M$17,1/(1+$C67)^$I$19:$M$19)+$N$17*(1+F$63)/($C67-F$63)/(1+$C67)^$M$19+$I$29+$I$30)/$I$32)*(1+$I$51)-$I$35 -> 962.09607 | G67: =((SUMPRODUCT($I$17:$M$17,1/(1+$C67)^$I$19:$M$19)+$N$17*(1+G$63)/($C67-G$63)/(1+$C67)^$M$19+$I$29+$I$30)/$I$32)*(1+$I$51)-$I$35 -> 986.13129 | H67: =((SUMPRODUCT($I$17:$M$17,1/(1+$C67)^$I$19:$M$19)+$N$17*(1+H$63)/($C67-H$63)/(1+$C67)^$M$19+$I$29+$I$30)/$I$32)*(1+$I$51)-$I$35 -> 1012.7304
C68: =$I$56+(2)*$C$61 -> 0.13874358 | D68: =((SUMPRODUCT($I$17:$M$17,1/(1+$C68)^$I$19:$M$19)+$N$17*(1+D$63)/($C68-D$63)/(1+$C68)^$M$19+$I$29+$I$30)/$I$32)*(1+$I$51)-$I$35 -> 892.51751 | E68: =((SUMPRODUCT($I$17:$M$17,1/(1+$C68)^$I$19:$M$19)+$N$17*(1+E$63)/($C68-E$63)/(1+$C68)^$M$19+$I$29+$I$30)/$I$32)*(1+$I$51)-$I$35 -> 910.46865 | F68: =((SUMPRODUCT($I$17:$M$17,1/(1+$C68)^$I$19:$M$19)+$N$17*(1+F$63)/($C68-F$63)/(1+$C68)^$M$19+$I$29+$I$30)/$I$32)*(1+$I$51)-$I$35 -> 930.07058 | G68: =((SUMPRODUCT($I$17:$M$17,1/(1+$C68)^$I$19:$M$19)+$N$17*(1+G$63)/($C68-G$63)/(1+$C68)^$M$19+$I$29+$I$30)/$I$32)*(1+$I$51)-$I$35 -> 951.56196 | H68: =((SUMPRODUCT($I$17:$M$17,1/(1+$C68)^$I$19:$M$19)+$N$17*(1+H$63)/($C68-H$63)/(1+$C68)^$M$19+$I$29+$I$30)/$I$32)*(1+$I$51)-$I$35 -> 975.22983
B70: Conferencia: centro - preco-alvo do DCF | C70: =F66-I36 -> 0 | D70: =IF(ABS(C70)<0.01,"ok","ERRO") -> ok
B72: Sensibilidade 2: preco-alvo (US$) - WACC (linhas) x MB normalizada (colunas)
C73: WACC \ MB | D73: =$N$7+(-2)*$G$61 -> 0.58 | E73: =$N$7+(-1)*$G$61 -> 0.6 | F73: =$N$7+(0)*$G$61 -> 0.62 | G73: =$N$7+(1)*$G$61 -> 0.64 | H73: =$N$7+(2)*$G$61 -> 0.66
C74: =$I$56+(-2)*$C$61 -> 0.11874358 | D74: =((SUMPRODUCT($I$17:$M$17,1/(1+$C74)^$I$19:$M$19)+(($N$6*D$73+$N$9)*(1-$N$12)+$N$14+$N$15+$N$16)*(1+$I$57)/($C74-$I$57)/(1+$C74)^$M$19+$I$29+$I$30)/$I$32)*(1+$I$51)-$I$35 -> 1033.2647 | E74: =((SUMPRODUCT($I$17:$M$17,1/(1+$C74)^$I$19:$M$19)+(($N$6*E$73+$N$9)*(1-$N$12)+$N$14+$N$15+$N$16)*(1+$I$57)/($C74-$I$57)/(1+$C74)^$M$19+$I$29+$I$30)/$I$32)*(1+$I$51)-$I$35 -> 1056.1104 | F74: =((SUMPRODUCT($I$17:$M$17,1/(1+$C74)^$I$19:$M$19)+(($N$6*F$73+$N$9)*(1-$N$12)+$N$14+$N$15+$N$16)*(1+$I$57)/($C74-$I$57)/(1+$C74)^$M$19+$I$29+$I$30)/$I$32)*(1+$I$51)-$I$35 -> 1078.9561 | G74: =((SUMPRODUCT($I$17:$M$17,1/(1+$C74)^$I$19:$M$19)+(($N$6*G$73+$N$9)*(1-$N$12)+$N$14+$N$15+$N$16)*(1+$I$57)/($C74-$I$57)/(1+$C74)^$M$19+$I$29+$I$30)/$I$32)*(1+$I$51)-$I$35 -> 1101.8017 | H74: =((SUMPRODUCT($I$17:$M$17,1/(1+$C74)^$I$19:$M$19)+(($N$6*H$73+$N$9)*(1-$N$12)+$N$14+$N$15+$N$16)*(1+$I$57)/($C74-$I$57)/(1+$C74)^$M$19+$I$29+$I$30)/$I$32)*(1+$I$51)-$I$35 -> 1124.6474
C75: =$I$56+(-1)*$C$61 -> 0.12374357 | D75: =((SUMPRODUCT($I$17:$M$17,1/(1+$C75)^$I$19:$M$19)+(($N$6*D$73+$N$9)*(1-$N$12)+$N$14+$N$15+$N$16)*(1+$I$57)/($C75-$I$57)/(1+$C75)^$M$19+$I$29+$I$30)/$I$32)*(1+$I$51)-$I$35 -> 993.59274 | E75: =((SUMPRODUCT($I$17:$M$17,1/(1+$C75)^$I$19:$M$19)+(($N$6*E$73+$N$9)*(1-$N$12)+$N$14+$N$15+$N$16)*(1+$I$57)/($C75-$I$57)/(1+$C75)^$M$19+$I$29+$I$30)/$I$32)*(1+$I$51)-$I$35 -> 1014.7902 | F75: =((SUMPRODUCT($I$17:$M$17,1/(1+$C75)^$I$19:$M$19)+(($N$6*F$73+$N$9)*(1-$N$12)+$N$14+$N$15+$N$16)*(1+$I$57)/($C75-$I$57)/(1+$C75)^$M$19+$I$29+$I$30)/$I$32)*(1+$I$51)-$I$35 -> 1035.9877 | G75: =((SUMPRODUCT($I$17:$M$17,1/(1+$C75)^$I$19:$M$19)+(($N$6*G$73+$N$9)*(1-$N$12)+$N$14+$N$15+$N$16)*(1+$I$57)/($C75-$I$57)/(1+$C75)^$M$19+$I$29+$I$30)/$I$32)*(1+$I$51)-$I$35 -> 1057.1852 | H75: =((SUMPRODUCT($I$17:$M$17,1/(1+$C75)^$I$19:$M$19)+(($N$6*H$73+$N$9)*(1-$N$12)+$N$14+$N$15+$N$16)*(1+$I$57)/($C75-$I$57)/(1+$C75)^$M$19+$I$29+$I$30)/$I$32)*(1+$I$51)-$I$35 -> 1078.3827
C76: =$I$56+(0)*$C$61 -> 0.12874357 | D76: =((SUMPRODUCT($I$17:$M$17,1/(1+$C76)^$I$19:$M$19)+(($N$6*D$73+$N$9)*(1-$N$12)+$N$14+$N$15+$N$16)*(1+$I$57)/($C76-$I$57)/(1+$C76)^$M$19+$I$29+$I$30)/$I$32)*(1+$I$51)-$I$35 -> 957.78452 | E76: =((SUMPRODUCT($I$17:$M$17,1/(1+$C76)^$I$19:$M$19)+(($N$6*E$73+$N$9)*(1-$N$12)+$N$14+$N$15+$N$16)*(1+$I$57)/($C76-$I$57)/(1+$C76)^$M$19+$I$29+$I$30)/$I$32)*(1+$I$51)-$I$35 -> 977.5106 | F76: =((SUMPRODUCT($I$17:$M$17,1/(1+$C76)^$I$19:$M$19)+(($N$6*F$73+$N$9)*(1-$N$12)+$N$14+$N$15+$N$16)*(1+$I$57)/($C76-$I$57)/(1+$C76)^$M$19+$I$29+$I$30)/$I$32)*(1+$I$51)-$I$35 -> 997.23667 | G76: =((SUMPRODUCT($I$17:$M$17,1/(1+$C76)^$I$19:$M$19)+(($N$6*G$73+$N$9)*(1-$N$12)+$N$14+$N$15+$N$16)*(1+$I$57)/($C76-$I$57)/(1+$C76)^$M$19+$I$29+$I$30)/$I$32)*(1+$I$51)-$I$35 -> 1016.9627 | H76: =((SUMPRODUCT($I$17:$M$17,1/(1+$C76)^$I$19:$M$19)+(($N$6*H$73+$N$9)*(1-$N$12)+$N$14+$N$15+$N$16)*(1+$I$57)/($C76-$I$57)/(1+$C76)^$M$19+$I$29+$I$30)/$I$32)*(1+$I$51)-$I$35 -> 1036.6888
C77: =$I$56+(1)*$C$61 -> 0.13374358 | D77: =((SUMPRODUCT($I$17:$M$17,1/(1+$C77)^$I$19:$M$19)+(($N$6*D$73+$N$9)*(1-$N$12)+$N$14+$N$15+$N$16)*(1+$I$57)/($C77-$I$57)/(1+$C77)^$M$19+$I$29+$I$30)/$I$32)*(1+$I$51)-$I$35 -> 925.28484 | E77: =((SUMPRODUCT($I$17:$M$17,1/(1+$C77)^$I$19:$M$19)+(($N$6*E$73+$N$9)*(1-$N$12)+$N$14+$N$15+$N$16)*(1+$I$57)/($C77-$I$57)/(1+$C77)^$M$19+$I$29+$I$30)/$I$32)*(1+$I$51)-$I$35 -> 943.69046 | F77: =((SUMPRODUCT($I$17:$M$17,1/(1+$C77)^$I$19:$M$19)+(($N$6*F$73+$N$9)*(1-$N$12)+$N$14+$N$15+$N$16)*(1+$I$57)/($C77-$I$57)/(1+$C77)^$M$19+$I$29+$I$30)/$I$32)*(1+$I$51)-$I$35 -> 962.09607 | G77: =((SUMPRODUCT($I$17:$M$17,1/(1+$C77)^$I$19:$M$19)+(($N$6*G$73+$N$9)*(1-$N$12)+$N$14+$N$15+$N$16)*(1+$I$57)/($C77-$I$57)/(1+$C77)^$M$19+$I$29+$I$30)/$I$32)*(1+$I$51)-$I$35 -> 980.50169 | H77: =((SUMPRODUCT($I$17:$M$17,1/(1+$C77)^$I$19:$M$19)+(($N$6*H$73+$N$9)*(1-$N$12)+$N$14+$N$15+$N$16)*(1+$I$57)/($C77-$I$57)/(1+$C77)^$M$19+$I$29+$I$30)/$I$32)*(1+$I$51)-$I$35 -> 998.90731
C78: =$I$56+(2)*$C$61 -> 0.13874358 | D78: =((SUMPRODUCT($I$17:$M$17,1/(1+$C78)^$I$19:$M$19)+(($N$6*D$73+$N$9)*(1-$N$12)+$N$14+$N$15+$N$16)*(1+$I$57)/($C78-$I$57)/(1+$C78)^$M$19+$I$29+$I$30)/$I$32)*(1+$I$51)-$I$35 -> 895.6405 | E78: =((SUMPRODUCT($I$17:$M$17,1/(1+$C78)^$I$19:$M$19)+(($N$6*E$73+$N$9)*(1-$N$12)+$N$14+$N$15+$N$16)*(1+$I$57)/($C78-$I$57)/(1+$C78)^$M$19+$I$29+$I$30)/$I$32)*(1+$I$51)-$I$35 -> 912.85554 | F78: =((SUMPRODUCT($I$17:$M$17,1/(1+$C78)^$I$19:$M$19)+(($N$6*F$73+$N$9)*(1-$N$12)+$N$14+$N$15+$N$16)*(1+$I$57)/($C78-$I$57)/(1+$C78)^$M$19+$I$29+$I$30)/$I$32)*(1+$I$51)-$I$35 -> 930.07058 | G78: =((SUMPRODUCT($I$17:$M$17,1/(1+$C78)^$I$19:$M$19)+(($N$6*G$73+$N$9)*(1-$N$12)+$N$14+$N$15+$N$16)*(1+$I$57)/($C78-$I$57)/(1+$C78)^$M$19+$I$29+$I$30)/$I$32)*(1+$I$51)-$I$35 -> 947.28562 | H78: =((SUMPRODUCT($I$17:$M$17,1/(1+$C78)^$I$19:$M$19)+(($N$6*H$73+$N$9)*(1-$N$12)+$N$14+$N$15+$N$16)*(1+$I$57)/($C78-$I$57)/(1+$C78)^$M$19+$I$29+$I$30)/$I$32)*(1+$I$51)-$I$35 -> 964.50066
B80: Conferencia: centro - preco-alvo do DCF | C80: =F76-I36 -> 0 | D80: =IF(ABS(C80)<0.01,"ok","ERRO") -> ok
B81: sanity: Ke fixo do cabecalho no roll-forward de 12m; so WACC/g/MB variam nas tabelas

Sheet Multiplos
B1: Multiplos - MU ao preco atual e peers
B2: MU: formulas sobre o modelo; peers: snapshot 06/out/26 (market.json), valores em azul com data/fonte no comentario; n.d. = nao encontrado
B4: US$ mn, exceto onde indicado | D4: FY26A | E4: FY27E | F4: FY28E
B5: Preco MU (US$, 06/out/26) | D5: =Premissas!$I$203 -> 1045.56
B6: Acoes em circulacao (mn) | D6: =Premissas!$I$205 -> 1129.39
B7: Mkt cap (US$ mn) | D7: =D5*D6 -> 1180845
B8: (-) Caixa e aplicacoes FY26A | D8: =BP!$H$5 -> 73453
B9: (+) Divida FY26A | D9: =BP!$H$19+BP!$H$22 -> 5179
B10: EV (US$ mn) | C10: ex-SCA dep. | D10: =D7-D8+D9 -> 1112571
B11: net cash | D11: =D8-D9 -> 68274
B13: MU - multiplos ao preco atual
B14: EV / Receita | D14: =$D$10/DRE!H5 -> 8.3533878 | E14: =$D$10/DRE!I5 -> 4.0776423 | F14: =$D$10/DRE!J5 -> 3.7021125
B15: EV / EBITDA | D15: =IF(DRE!H16<=0,"n.m.",$D$10/DRE!H16) -> 10.221797 | E15: =IF(DRE!I16<=0,"n.m.",$D$10/DRE!I16) -> 4.6467687 | F15: =IF(DRE!J16<=0,"n.m.",$D$10/DRE!J16) -> 4.2008701
B16: P/E GAAP | D16: =IF(DRE!H31<=0,"n.m.",$D$5/DRE!H31) -> 14.06646 | E16: =IF(DRE!I31<=0,"n.m.",$D$5/DRE!I31) -> 6.0005018 | F16: =IF(DRE!J31<=0,"n.m.",$D$5/DRE!J31) -> 4.9754036
B17: P/E non-GAAP | D17: =IF(DRE!H39<=0,"n.m.",$D$5/DRE!H39) -> 13.844809 | E17: =IF(DRE!I39<=0,"n.m.",$D$5/DRE!I39) -> 5.9489604 | F17: =IF(DRE!J39<=0,"n.m.",$D$5/DRE!J39) -> 4.9308877
B18: P/B | D18: =$D$7/BP!H26 -> 8.5334736 | E18: =$D$7/BP!I26 -> 4.7452135 | F18: =$D$7/BP!J26 -> 3.8941495
B19: FCF yield | D19: =FC!H23/$D$7 -> 0.052763063 | E19: =FC!I23/$D$7 -> 0.12084824 | F19: =FC!J23/$D$7 -> 0.14688911
B20: Dividend yield | D20: =DRE!H42/$D$5 -> 0.00050690539 | E20: =DRE!I42/$D$5 -> 0.00066911512 | F20: =DRE!J42/$D$5 -> 0.0008631585
B22: Peers (preco e mkt cap de 06/out/26; multiplos conforme data na nota)
B23: Empresa | C23: Ticker | D23: Preco (moeda local) | E23: Mkt cap (US$ bn) | F23: EV (US$ bn) | G23: P/E fwd | H23: P/E TTM | I23: EV/EBITDA fwd | J23: EV/EBITDA TTM | K23: P/B
B24: Samsung Electronics | C24: 005930 KS | D24: 272000 | E24: 1291.5 | F24: n.d. | G24: 5.3 | H24: 12.23 | I24: n.d. | J24: n.d. | K24: 3
B25: SK hynix | C25: 000660 KS | D25: 1773000 | E25: 966.3 | F25: 951.1 | G25: 4.88 | H25: n.d. | I25: n.d. | J25: 8.86 | K25: 5.1
B26: SanDisk | C26: SNDK | D26: 1660.46 | E26: 243.12 | F26: 244.36 | G26: 7.97 | H26: 24.63 | I26: 5.58 | J26: 19.27 | K26: n.d.
B27: Kioxia | C27: 285A JP | D27: 18735 | E27: 195 | F27: n.d. | G27: 4.34 | H27: 17.74 | I27: n.d. | J27: 13.23 | K27: 13.21
B28: Western Digital | C28: WDC | D28: 411.04 | E28: 149.7 | F28: 165.1 | G28: 19.55 | H28: 17 | I28: n.d. | J28: 15.81 | K28: 18.8
B29: Nvidia | C29: NVDA | D29: 239.24 | E29: 5780 | F29: 5750 | G29: 19.78 | H29: 30.25 | I29: n.d. | J29: 28.59 | K29: 24.67
B30: Media peers | E30: =IFERROR(AVERAGE(E24:E29),"n.d.") -> 1437.6033 | F30: =IFERROR(AVERAGE(F24:F29),"n.d.") -> 1777.64 | G30: =IFERROR(AVERAGE(G24:G29),"n.d.") -> 10.303333 | H30: =IFERROR(AVERAGE(H24:H29),"n.d.") -> 20.37 | I30: =IFERROR(AVERAGE(I24:I29),"n.d.") -> 5.58 | J30: =IFERROR(AVERAGE(J24:J29),"n.d.") -> 17.152 | K30: =IFERROR(AVERAGE(K24:K29),"n.d.") -> 12.956
B31: Mediana peers | E31: =IFERROR(MEDIAN(E24:E29),"n.d.") -> 604.71 | F31: =IFERROR(MEDIAN(F24:F29),"n.d.") -> 597.73 | G31: =IFERROR(MEDIAN(G24:G29),"n.d.") -> 6.635 | H31: =IFERROR(MEDIAN(H24:H29),"n.d.") -> 17.74 | I31: =IFERROR(MEDIAN(I24:I29),"n.d.") -> 5.58 | J31: =IFERROR(MEDIAN(J24:J29),"n.d.") -> 15.81 | K31: =IFERROR(MEDIAN(K24:K29),"n.d.") -> 13.21
B32: Micron (modelo, preco atual) | C32: MU US | D32: =D5 -> 1045.56 | E32: =D7/1000 -> 1180.845 | F32: =D10/1000 -> 1112.571 | G32: =E17 -> 5.9489604 | H32: =D17 -> 13.844809 | I32: =E15 -> 4.6467687 | J32: =D15 -> 10.221797 | K32: =D18 -> 8.5334736
B33: MU vs mediana dos peers (premio / desconto) | G33: =IFERROR(G32/G31-1,"n.d.") -> -0.10339708 | H33: =IFERROR(H32/H31-1,"n.d.") -> -0.21957106 | I33: =IFERROR(I32/I31-1,"n.d.") -> -0.16724575 | J33: =IFERROR(J32/J31-1,"n.d.") -> -0.35346005 | K33: =IFERROR(K32/K31-1,"n.d.") -> -0.35401411
B34: P/E fwd MU = preco / EPS non-GAAP FY27E (FY27 termina set/27); peers em base calendario/fiscal propria - comparacao indicativa
B35: FX 06/out/26: USDKRW 1337.34 | USDJPY 158.15 (tradingeconomics / investing.com)

Sheet Trimestral
B1: Trimestral - 1T24 a 4T26 e guidance 1T27
B2: 8-K/press releases, 10-Q MD&A e prepared remarks (quarterly.json); 4T26 com 14 semanas; valores estimados/derivados em comentario
B4: US$ mn, exceto onde indicado | D4: 1T24 | E4: 2T24 | F4: 3T24 | G4: 4T24 | H4: 1T25 | I4: 2T25 | J4: 3T25 | K4: 4T25 | L4: 1T26 | M4: 2T26 | N4: 3T26 | O4: 4T26 | P4: 1T27 guid.
B5: Rec. liq. | C5: 8-K | D5: 4726 | E5: 5824 | F5: 6811 | G5: 7750 | H5: 8709 | I5: 8053 | J5: 9301 | K5: 11315 | L5: 13643 | M5: 23860 | N5: 41456 | O5: 54229 | P5: 61500
B6: DRAM | D6: 3470 | E6: 4200 | F6: 4700 | G6: 5300 | H6: 6400 | I6: 6100 | J6: 7100 | K6: 9000 | L6: 10812 | M6: 18800 | N6: 31300 | O6: 39800 | P6: n.d.
B7: NAND | D7: 1260 | E7: 1600 | F7: 2100 | G7: 2400 | H7: 2200 | I7: 1900 | J7: 2200 | K7: 2300 | L7: 2743 | M7: 5000 | N7: 9900 | O7: 14100 | P7: n.d.
B8: cresc. t/t | E8: =E5/D5-1 -> 0.23233178 | F8: =F5/E5-1 -> 0.16947115 | G8: =G5/F5-1 -> 0.13786522 | H8: =H5/G5-1 -> 0.12374194 | I8: =I5/H5-1 -> -0.075324377 | J8: =J5/I5-1 -> 0.1549733 | K8: =K5/J5-1 -> 0.21653586 | L8: =L5/K5-1 -> 0.20574459 | ... P8: =P5/O5-1 -> 0.13407955
B9: MB GAAP | D9: -0.007 | E9: 0.185 | F9: 0.269 | G9: 0.353 | H9: 0.384 | I9: 0.368 | J9: 0.377 | K9: 0.447 | L9: 0.56 | M9: 0.744 | N9: 0.846 | O9: 0.868 | P9: 0.8595
B10: MB non-GAAP | D10: 0.008 | E10: 0.2 | F10: 0.281 | G10: 0.365 | H10: 0.395 | I10: 0.379 | J10: 0.39 | K10: 0.457 | L10: 0.568 | M10: 0.749 | N10: 0.849 | O10: 0.87 | P10: 0.8625
B11: Desp. op. non-GAAP | D11: 992 | E11: 959 | F11: 973 | G11: 1084 | H11: 1047 | I11: 1046 | J11: 1133 | K11: 1214 | L11: 1334 | M11: 1421 | N11: 1518 | O11: 2568 | P11: 2060
B12: EBIT non-GAAP | D12: -955 | E12: 204 | F12: 941 | G12: 1745 | H12: 2394 | I12: 2007 | J12: 2490 | K12: 3955 | L12: 6419 | M12: 16450 | N12: 33681 | O12: 44636 | P12: =P5*P10-P11 -> 50983.75
B13: LL non-GAAP | D13: -1050 | E13: 476 | F13: 702 | G13: n.d. | H13: 2040 | I13: 1780 | J13: 2180 | K13: 3470 | L13: 5480 | M13: 14020 | N13: 28860 | O13: 38400 | P13: =P14*P16 -> 43872.5
B14: EPS non-GAAP (US$) | D14: -0.95 | E14: 0.42 | F14: 0.62 | G14: 1.18 | H14: 1.79 | I14: 1.56 | J14: 1.91 | K14: 3.03 | L14: 4.78 | M14: 12.2 | N14: 25.11 | O14: 33.42 | P14: 38.15
B15: EPS GAAP (US$) | D15: -1.12 | E15: 0.71 | F15: 0.3 | G15: 0.79 | H15: 1.67 | I15: 1.41 | J15: 1.68 | K15: 2.83 | L15: 4.6 | M15: 12.07 | N15: 24.67 | O15: 32.87 | P15: 37.84
B16: Acoes diluidas (mn) | D16: 1098 | E16: 1117 | F16: 1132 | G16: 1123 | H16: 1140 | I16: 1141 | J16: 1125 | K16: 1145 | L16: 1146 | M16: 1142 | N16: 1145 | O16: 1147 | P16: 1150
B17: Capex liq. | D17: 1730 | E17: 1250 | F17: 2057 | G17: 3080 | H17: 3130 | I17: 3090 | J17: 2700 | K17: 4930 | L17: 4500 | M17: 5000 | N17: 7100 | O17: 10770 | P17: 11500
B18: FCF ajustado | D18: -333 | E18: -29 | F18: 425 | G18: 323 | H18: 112 | I18: 857 | J18: 1900 | K18: 803 | L18: 3900 | M18: 6900 | N18: 18300 | O18: 33200 | P18: n.d.
B19: Caixa e aplicacoes | D19: 9840 | E19: 9720 | F19: 9220 | G19: 9160 | H19: 8750 | I19: 9600 | J19: 12200 | K19: 11940 | L19: 12050 | M19: 16700 | N19: 30200 | O19: 73480 | P19: n.d.
B20: Divida total | D20: 13505 | E20: 13722 | F20: 13258 | G20: 13400 | H20: 13800 | I20: n.d. | J20: 15500 | K20: 14600 | L20: 11800 | M20: 10100 | N20: 5700 | O20: 5179 | P20: n.d.
B21: DIO (dias, empresa) | D21: n.d. | E21: n.d. | F21: n.d. | G21: 158 | H21: 149 | I21: 158 | J21: n.d. | K21: 124 | L21: 126 | M21: 123 | N21: 120 | O21: 129 | P21: n.d.
B22: DPS (US$) | D22: 0.115 | E22: 0.115 | F22: 0.115 | G22: 0.115 | H22: 0.115 | I22: 0.115 | J22: 0.115 | K22: 0.115 | L22: 0.115 | M22: 0.115 | N22: 0.15 | O22: 0.15 | P22: 0.15
B24: Bits e ASP t/t (texto literal do 10-Q / prepared remarks)
B25: DRAM bits t/t | C25: 10-Q/remarks | D25: low-20s percent range increase in bit shipments | E25: bit shipments increased in the low single-digit percentage range | F25: a mid-single-digit percent range decrease in bit shipments | G25: n.d. | H25: a low-double-digit percent range increase in bit shipments | I25: bit shipments decreasing in the high-single-digit percentage range | J25: an over 20% increase in bit shipments | K25: bit shipments increased in the low-teens percentage range | L25: bit shipments up slightly | M25: bit shipments increased in the mid-single-digit percentage range | N25: bit shipments increased in the low-single-digit percentage range | O25: Bit shipments increased in the mid-single-digit percentage range sequentially
B26: DRAM ASP t/t | D26: increases in average selling prices in the low single-digit-percent range | E26: prices increased in the high-teens percentage range | F26: increases in average selling prices by approximately 20% | G26: n.d. | H26: a high-single-digit percent range increase in average selling prices | I26: prices increasing in the mid-single-digit percentage range as a result of improving portfolio mix | J26: a low-single-digit percent range decrease in average selling prices primarily due to a higher consumer-oriented revenue mix | K26: prices increased in the low-double-digit percentage range (tight supply, pricing actions, improved mix) | L26: prices up approximately 20% sequentially | M26: prices increased in the mid-60s percentage range | N26: prices increased in the low-60s percentage range | O26: pricing rose in the high-teens percentage range amid tight industry supply
B27: NAND bits t/t | D27: decreases in bit shipments in the mid-teens percent range after record NAND bit shipments in the fourth quarter of 2023 | E27: bit shipments decreased in the low single-digit percentage range | F27: a high-single-digit percent range increase in bit shipments | G27: n.d. | H27: a low-single-digit percent range decrease in bit shipments | I27: modestly higher bit shipments | J27: a mid-20% range increase in bit shipments | K27: bit shipments decreased in the mid-single-digit percentage range | L27: NAND bit shipments increased mid to high single digits sequentially | M27: NAND bit shipments increased in the low single-digit percentage range | N27: bit shipments increased in the mid-single-digit percentage range | O27: NAND bit shipments rose about 10%
B28: NAND ASP t/t | D28: an approximate 20% increase in average selling prices | E28: prices increased by more than 30% | F28: an approximate 20% increase in average selling prices | G28: n.d. | H28: a low-single-digit percent range decrease in average selling prices | I28: a high-teens percentage decrease in average selling prices | J28: a high-single-digit percent range decrease in average selling prices | K28: prices increased in the high-single-digit percentage range driven by improved mix | L28: prices up mid-teens percentage range versus prior quarter | M28: prices increased in the high-70s percentage range | N28: prices increased in the mid-80s percentage range | O28: prices increased approximately 30% sequentially
B29: HBM (comentario) | D29: HBM3E in qualification; no HBM revenue disclosed | E29: HBM3E volume production started; sold out for CY2024 (per remarks) | F29: HBM sold out for CY2024 and CY2025; >$100M HBM3E revenue in FQ3 (per remarks) | G29: Data center SSD revenue >$1B for first time; HBM ramping (HBM3E 8-high); no HBM $ disclosed | H29: HBM revenue more than doubled sequentially; shipments ahead of plan; data center revenue >50% of total for first time | I29: HBM revenue grew more than 50% sequentially to a new milestone of over $1 billion of quarterly revenue | J29: nearly 50% sequential growth in HBM revenue; exited FQ3 at HBM run-rate exceeding $6B annualized; data center revenue more than doubled y/y | K29: HBM revenue grew to nearly $2 billion in fiscal Q4, implying an annualized run rate of nearly $8 billion, driven by the ramp of HBM3E products; HBM share 'in line with our overall DRAM share' in CQ3'25; six HBM customers | L29: All CY2026 HBM price/volume agreements finalized; HBM TAM ~$35B (2025) -> ~$100B by 2028 (two years earlier than prior view); HBM4 ramp expected 2H CY2026 | M29: HBM revenue reached a new high (no $ disclosed); volume shipments of HBM4 36GB 12-high began in CQ1 2026 for NVIDIA Vera Rubin; data center NAND revenue more than doubled sequentially | N29: HBM4 12-high volume ramp tracking 2x as fast as HBM3E 12-high; >$1B cumulative HBM4 revenue shipped; CY2026 HBM supply sold out under multi-year contracts; 16 Strategic Customer Agreements signed (~$18B cash deposits + ~$4B letters of credit expected); data center revenue >$25B in the quarter | O29: HBM revenue for fiscal Q4 2026 grew faster than total company revenue in the quarter as we ramp HBM shipments across a growing number of customers; agreements completed for the vast majority of CY2027 HBM bit supply with significant price increases y/y, narrowing the GM gap with conventional DRAM; HBM4 ramp on track; custom HBM4E (NV-HBM) with NVIDIA; data center SSD revenue nearly $10B (>10x y/y, >2/3 of NAND) | P29: CY27 HBM contratado com alta de preco relevante; ~75% dos embarques FY27 comprometidos
B31: Receita por BU (nova estrutura a partir do 4T25)
B32: CMBU | K32: 4543 | L32: 5300 | M32: 7749 | N32: 13769 | O32: 16283
B33: CDBU | K33: 1577 | L33: 2379 | M33: 5690 | N33: 11524 | O33: 18002
B34: MCBU | K34: 3760 | L34: 4300 | M34: 7700 | N34: 11521 | O34: 13114
B35: AEBU | K35: 1435 | L35: 1700 | M35: 2700 | N35: 4634 | O35: 6824
B36: Segmentos legados (ate 3T25)
B37: CNBU | D37: 1737 | E37: 2185 | F37: 2570 | H37: 4395 | I37: 4564 | J37: 5069
B38: MBU | D38: 1293 | E38: 1598 | F38: 1590 | H38: 1527 | I38: 1068 | J38: 1551
B39: EBU | D39: 1037 | E39: 1111 | F39: 1290 | I39: 1025 | J39: 1227
B40: SBU | D40: 653 | E40: 905 | F40: 1350 | I40: 1392 | J40: 1451
B42: Conferencia FY27E vs guidance 1T27 e consenso
B43: Guidance 1T27 x 4 (receita) | D43: =4*P5 -> 246000
B44: Receita FY27E (modelo) | D44: =DRE!$I$5 -> 272846.64
B45: modelo / (4 x guia) - 1 | C45: Base: +11% (crescimento sequencial guiado) | D45: =D44/D43-1 -> 0.10913269
B46: Receita FY27E / 4 vs guia 1T27 (sanity) | D46: =D44/4 -> 68211.66 | E46: =D46/P5-1 -> 0.10913269
B47: MB GAAP guia 1T27 (piso do ano, CFO) | D47: =P9 -> 0.8595
B48: MB GAAP FY27E (modelo) | D48: =DRE!$I$9 -> 0.86806508
B49: EPS non-GAAP guia 1T27 x 4 | D49: =4*P14 -> 152.6
B50: EPS non-GAAP FY27E (modelo) | D50: =DRE!$I$39 -> 175.75508
B51: Consenso receita FY27E | D51: =Premissas!$I$207 -> 275010
B52: modelo vs consenso | D52: =D44/D51-1 -> -0.0078664703
B53: Consenso EPS FY27E | D53: =Premissas!$I$208 -> 176.15
B54: modelo vs consenso | D54: =D50/D53-1 -> -0.0022419611

Sheet Ciclo
B1: Ciclo - historico FY2013-FY2026 (referencia visual para a MB normalizada do DCF; nao linkado)
B2: 10-K/8-K por ano (sector_cycle.json); capex = 'expenditures for PP&E' (bruto); FY26A nao auditado; est. = valor estimado/arredondado
B4: US$ mn, exceto onde indicado | D4: FY13A | E4: FY14A | F4: FY15A | G4: FY16A | H4: FY17A | I4: FY18A | J4: FY19A | K4: FY20A | L4: FY21A | M4: FY22A | N4: FY23A | O4: FY24A | P4: FY25A | Q4: FY26A | S4: Media FY13-25 | T4: Mediana FY13-25 | U4: Media ex-picos
B5: Rec. liq. | D5: 9073 | E5: 16358 | F5: 16192 | G5: 12399 | H5: 20322 | I5: 30391 | J5: 23406 | K5: 21435 | L5: 27705 | M5: 30758 | N5: 15540 | O5: 25111 | P5: 37378 | Q5: 133188 | S5: =AVERAGE(D5:P5) -> 22005.231 | T5: =MEDIAN(D5:P5) -> 21435 | U5: =AVERAGE(D5:H5,J5:L5,N5:P5) -> 20447.182
B6: cresc. a/a | E6: =E5/D5-1 -> 0.80293178 | F6: =F5/E5-1 -> -0.01014794 | G6: =G5/F5-1 -> -0.23425148 | H6: =H5/G5-1 -> 0.63900315 | I6: =I5/H5-1 -> 0.49547289 | J6: =J5/I5-1 -> -0.22983778 | K6: =K5/J5-1 -> -0.084209177 | L6: =L5/K5-1 -> 0.29251225 | ... Q6: =Q5/P5-1 -> 2.5632725
B7: Lucro bruto | D7: 1847 | E7: 5437 | F7: 5215 | G7: 2505 | H7: 8436 | I7: 17891 | J7: 10702 | K7: 6552 | L7: 10423 | M7: 13898 | N7: -1416 | O7: 5613 | P7: 14873 | Q7: 107504
B8: MB | D8: =D7/D5 -> 0.20357103 | E8: =E7/E5 -> 0.3323756 | F8: =F7/F5 -> 0.32207263 | G8: =G7/G5 -> 0.20203242 | H8: =H7/H5 -> 0.41511662 | I8: =I7/I5 -> 0.58869402 | J8: =J7/J5 -> 0.45723319 | K8: =K7/K5 -> 0.3056683 | ... Q8: =Q7/Q5 -> 0.8071598 | S8: =AVERAGE(D8:P8) -> 0.32193409 | T8: =MEDIAN(D8:P8) -> 0.3323756 | U8: =AVERAGE(D8:H8,J8:L8,N8:P8) -> 0.28587265
B9: EBIT | D9: 236 | E9: 3087 | F9: 2998 | G9: 168 | H9: 5868 | I9: 14994 | J9: 7376 | K9: 3003 | L9: 6283 | M9: 9702 | N9: -5745 | O9: 1304 | P9: 9770 | Q9: 99340
B10: mg EBIT | D10: =D9/D5 -> 0.026011242 | E10: =E9/E5 -> 0.188715 | F10: =F9/F5 -> 0.18515316 | G10: =G9/G5 -> 0.01354948 | H10: =H9/H5 -> 0.28875111 | I10: =I9/I5 -> 0.49336975 | J10: =J9/J5 -> 0.31513287 | K10: =K9/K5 -> 0.14009797 | ... Q10: =Q9/Q5 -> 0.74586299 | S10: =AVERAGE(D10:P10) -> 0.16435499 | T10: =MEDIAN(D10:P10) -> 0.188715 | U10: =AVERAGE(D10:H10,J10:L10,N10:P10) -> 0.12071046
B11: LL | D11: 1190 | E11: 3045 | F11: 2899 | G11: -276 | H11: 5089 | I11: 14135 | J11: 6313 | K11: 2687 | L11: 5861 | M11: 8687 | N11: -5833 | O11: 778 | P11: 8539 | Q11: 84969 | S11: =AVERAGE(D11:P11) -> 4085.6923 | T11: =MEDIAN(D11:P11) -> 3045 | U11: =AVERAGE(D11:H11,J11:L11,N11:P11) -> 2753.8182
B12: mg liquida | D12: =D11/D5 -> 0.13115838 | E12: =E11/E5 -> 0.18614745 | F12: =F11/F5 -> 0.17903903 | G12: =G11/G5 -> -0.02225986 | H12: =H11/H5 -> 0.25041827 | I12: =I11/I5 -> 0.4651048 | J12: =J11/J5 -> 0.26971717 | K12: =K11/K5 -> 0.12535573 | ... Q12: =Q11/Q5 -> 0.63796288 | S12: =AVERAGE(D12:P12) -> 0.15098002 | T12: =MEDIAN(D12:P12) -> 0.18614745 | U12: =AVERAGE(D12:H12,J12:L12,N12:P12) -> 0.11047317
B13: Capex (bruto, PP&E) | D13: 1244 | E13: 2658 | F13: 4021 | G13: 5817 | H13: 4734 | I13: 8879 | J13: 9780 | K13: 8223 | L13: 10030 | M13: 12067 | N13: 7676 | O13: 8386 | P13: 15857 | Q13: 30712 | S13: =AVERAGE(D13:P13) -> 7644 | T13: =MEDIAN(D13:P13) -> 8223 | U13: =AVERAGE(D13:H13,J13:L13,N13:P13) -> 7129.6364
B14: Capex / receita | D14: =D13/D5 -> 0.13711011 | E14: =E13/E5 -> 0.1624893 | F14: =F13/F5 -> 0.24833251 | G14: =G13/G5 -> 0.46915074 | H14: =H13/H5 -> 0.23294951 | I14: =I13/I5 -> 0.29215886 | J14: =J13/J5 -> 0.41784158 | K14: =K13/K5 -> 0.38362491 | ... Q14: =Q13/Q5 -> 0.23059134 | S14: =AVERAGE(D14:P14) -> 0.33462681 | T14: =MEDIAN(D14:P14) -> 0.36202851 | U14: =AVERAGE(D14:H14,J14:L14,N14:P14) -> 0.33324264
B15: FCO | D15: 1811 | E15: 5699 | F15: 5208 | G15: 3168 | H15: 8153 | I15: 17400 | J15: 13189 | K15: 8306 | L15: 12470 | M15: 15181 | N15: 1559 | O15: 8507 | P15: 17525 | Q15: 89675 | S15: =AVERAGE(D15:P15) -> 9090.4615 | T15: =MEDIAN(D15:P15) -> 8306 | U15: =AVERAGE(D15:H15,J15:L15,N15:P15) -> 7781.3636
B16: FCF simples (FCO - capex bruto) | D16: =D15-D13 -> 567 | E16: =E15-E13 -> 3041 | F16: =F15-F13 -> 1187 | G16: =G15-G13 -> -2649 | H16: =H15-H13 -> 3419 | I16: =I15-I13 -> 8521 | J16: =J15-J13 -> 3409 | K16: =K15-K13 -> 83 | ... Q16: =Q15-Q13 -> 58963 | S16: =AVERAGE(D16:P16) -> 1446.4615 | T16: =MEDIAN(D16:P16) -> 1668 | U16: =AVERAGE(D16:H16,J16:L16,N16:P16) -> 651.72727
B17: DRAM % receita | D17: 0.481 | E17: 0.682 | F17: 0.64 | G17: 0.581 | H17: 0.638 | I17: 0.699 | J17: 0.65 | K17: 0.677 | L17: 0.723 | M17: 0.728 | N17: 0.706 | O17: 0.701 | P17: 0.765 | Q17: 0.756
B18: Flag | F18: 53s | J18: est. | K18: 53s | L18: est. | O18: est. | Q18: est. 53s | U18: ex FY18, FY22
B20: Comentario de ciclo (sector_cycle.json, enxuto)
B21: Ciclo 2016-18. Vale no FY16: ASP de DRAM -35% a/a e NAND -20%, GM 20%, EBIT 1% da receita, prejuizo de US$276 mn, fruto da fraqueza de PC e do excesso de bits pos-Elpida.
B22: A subida levou dois anos: GM 41,5% no FY17 e 59% no FY18 (EBIT 49%, lucro US$14,1 bi), com ASP de DRAM +35% e bits +20% no FY18; o pico de margem durou cerca de um ano fiscal e o capex dobrou (US$4,7 bi -> US$8,9 bi) junto com o da industria, semeando a queda.
B23: Ciclo 2019-20. ASP de DRAM ~-30% no FY19 e mais mid-30s% no FY20 (NAND -mid-40s% no FY19); GM caiu de 59% para 46% e 31%, EBIT de 49% para 31% e 14%. Ciclo raso em lucro: sem prejuizo, FCF ajustado positivo (US$0,4 bi no FY20), porque cortes de capex/wafers vieram cedo e cloud/mobile absorveram bits (+low-30s% no FY20).
B24: Do vale (FY20) ao pico seguinte foram ~2 anos: GM 37,6% no FY21 e 45% no FY22.
B25: Ciclo 2021-23. Pico curto (~3 trimestres em 2022; GM 45%, EBIT 31,5%, capex 39% da receita) seguido do colapso mais profundo da historia recente: receita -49% no FY23, ASP de DRAM -high-40s% e NAND -low-50s%, GM -9% (incl. baixa de estoque de US$1,8 bi), EBIT -37%, prejuizo de US$5,8 bi, FCF ajustado -US$5,5 bi.
B26: Resposta: capex -36%, reestruturacao com headcount -15%; do vale (FY23) ate GM de 40% (FY25) foram ~2 anos, e o pico anterior de 45% so foi superado no FY26.
B27: Ciclo 2024-26. Comecou como ciclo de HBM/servidor de IA e virou choque de oferta generalizado: ASP de DRAM +low-40s% no FY25 e +~20% (FQ1-26), +low-60s% (FQ3-26) e +high-teens% (FQ4-26) t/t; receita FY26 de US$133 bi (3,5x o recorde anterior, com 53 semanas), GM 81% no ano e 87% na saida, EBIT 75% da receita, DRAM 76% do mix. Nenhum ciclo anterior passou de 59% de GM.
B28: O que difere: (1) HBM, muito mais intensiva em wafers por bit, vendida ate CY27 com preco em alta e sustentada por take-or-pay (26 SCAs, >35% da receita ate 2030 com floor; US$12,7 bi de depositos de clientes no balanco; >75% do output do FY27 comprometido).
B29: (2) Disciplina de capex: apesar de US$30,7 bi no FY26, a intensidade caiu para 23% da receita (vs 39% no FY22 e 42% no FY19), e o incremento do FY27 e majoritariamente obra civil, com cleanroom chegando so em meados de 2027 (ID1), fim de 2028 (ID2, Hiroshima) e 2030 (NY).
B30: (3) Retornos decrescentes das transicoes de no (1-gamma) limitam o crescimento de bits por wafer; a propria Micron diz nao ter visibilidade de quando oferta e demanda se equilibram e espera mercado apertado em FY27 e FY28.
B31: (4) CXMT ja tem 7-10% de share e ~350k wpm ate fim de 2026 (perto da Micron), mas com DUV e HBM3 no melhor caso no fim de 2026: pressiona DDR4/DDR5 commodity, nao HBM. (5) Em NAND, eSSD passou a 48% dos bits e YMTC a 14% de share; a TrendForce ja ve afrouxamento de oferta de NAND no 2S27.
... B36: Referencia: MB normalizada do DCF (Base 62% / Bull 68% / Bear 47%) vs media FY13-25 ~33% e picos de 45-59% (FY18, FY22) - input independente na aba Premissas.

Sheet Notas
B1: Notas - racional, fontes, controle de versao, pendencias e legenda
B2: Modelo Micron (MU) v1 - 07/out/26 - LF
B4: Controle de versao
B5: v1 - 07/out/26 - modelo inicial pos-4T26 - LF
B7: Legenda de cores
B8: Azul: valor hardcoded (historico reportado, premissa, snapshot de mercado)
B9: Preto: formula
B10: Verde: link direto para outra aba
B11: Cinza italico: linhas de memoria / crescimento / notas
B12: Fundo amarelo: seletor de cenario (Premissas!D4)
B14: Racional (racional.md, 07/out/26)
B15: Arquivos: premissas_final.json (premissas), premissas_lentes.md (tres lentes), scripts/build_premissas_final.py (esboco de P&L/caixa que valida as premissas). US$ bi salvo indicacao; ano fiscal termina no inicio de setembro.
... B395: https://www.fabricatedknowledge.com/p/micron-and-stmicroelectronics-investor
